Workbook

Sheet Overview
A1: San Diego Gulls — Forensic Model Workbook
A2: Historical base: FY2021-22 to FY2025-26 public anchors + modeled estimates | Baseline projection: FY2026-27
A4: 2025-26 Avg Attendance | C4: 2025-26 Gross Revenue | E4: 2026-27 Gross Revenue | G4: 2026-27 EBITDA | I4: 2026-27 Valuation
A5: =Master_Model!I3 -> 7403 | C5: =Master_Model!I49 -> 11210427 | E5: =Master_Model!J49 -> 12031865 | G5: =Master_Model!J95 -> 1682309 | I5: =Master_Model!J99 -> 38501968
A8: What this workbook does • Converts publicly available Gulls data into a clean operating model. • Separates public facts from logical estimates and projections. • Gives an upside framework for attendance, ticket yield, ancillary spend and sponsorship. Modeling discipline • Public items are linked to the Assumptions and Source_Log tabs. • Private economics (EBITDA, parking share, sponsorship mix, parent subsidy) are clearly labeled as modeled estimates. | G8: High-level readout • Attendance recovered from 6,992 in 2021-22 to 7,403 in 2025-26. • STM entry price rose from $476 to $614 over the same span. • Promotional intensity expanded from 13 theme nights to 28 announced nights. • The 2026-27 upside cases show how operational discipline can push revenue, EBITDA and implied franchise value higher.

Sheet Assumptions
A1: San Diego Gulls — Assumptions & Public Inputs
A2: Blue-font cells are hardcoded historical inputs / modeled estimates. Black-font cells in 2026-27 are formula-driven projections where applicable.
A4: Category | B4: Driver | C4: 2021-22 | D4: 2022-23 | E4: 2023-24 | F4: 2024-25 | G4: 2025-26 | H4: 2026-27 | I4: Unit | J4: Source / Method | K4: Status
A5: CONTROL | B5: 2026-27 attendance growth assumption | H5: 0.03 | I5: pct | J5: Model control | K5: Control
A6: CONTROL | B6: 2026-27 WATP growth assumption | H6: 0.032 | I6: pct | J6: Model control | K6: Control
A7: CONTROL | B7: 2026-27 sponsorship growth assumption | H7: 0.093 | I7: pct | J7: Model control | K7: Control
A8: CONTROL | B8: 2026-27 per-cap F&B growth assumption | H8: 0.032 | I8: pct | J8: Model control | K8: Control
A9: CONTROL | B9: 2026-27 merch per-cap growth assumption | H9: 0.044 | I9: pct | J9: Model control | K9: Control
A10: CONTROL | B10: 2026-27 STM price growth assumption | H10: 0.03 | I10: pct | J10: Model control | K10: Control
A11: CONTROL | B11: 2026-27 single-game price growth assumption | H11: 0.043 | I11: pct | J11: Model control | K11: Control
A12: CONTROL | B12: 2026-27 website traffic growth assumption | H12: 0.08 | I12: pct | J12: Model control | K12: Control
A13: ATTENDANCE | B13: Average attendance | C13: 6992 | D13: 6953 | E13: 7249 | F13: 7262 | G13: 7403 | H13: =ROUND(G13*(1+$H$5),0) -> 7625 | I13: fans/game | J13: https://www.hockeydb.com/stte/san-diego-gulls-11619.html | K13: Public/Projection
A14: ATTENDANCE | B14: Home games | C14: 34 | D14: 36 | E14: 36 | F14: 36 | G14: 36 | H14: 36 | I14: games | J14: https://www.sandiegogulls.com/news/detail/san-diego-gulls-2021-22-schedule-announced | K14: Public
A15: VENUE | B15: Hockey seating capacity | C15: 12920 | D15: 12920 | E15: 12920 | F15: 12920 | G15: 12920 | H15: 12920 | I15: seats | J15: https://www.sandiegogulls.com/assets/doc/2021-22-San-Diego-Gulls-Media-Guide-compressed-92470e4558.pdf | K15: Context
A16: VENUE | B16: General venue capacity | C16: 14000 | D16: 14000 | E16: 14000 | F16: 14000 | G16: 14000 | H16: 14000 | I16: seats | J16: https://pechangaarenasd.com/about/ | K16: Public
A17: SCHEDULE | B17: Home weekend dates | C17: 23 | D17: 23 | E17: 26 | F17: 25 | G17: 25 | H17: 25 | I17: dates | J17: Multiple official schedule releases on sandiegogulls.com | K17: Public
A18: SCHEDULE | B18: Friday home games | C18: 11 | D18: 12 | E18: 12 | F18: 9 | G18: 10 | H18: 10 | I18: games | J18: Multiple official schedule releases on sandiegogulls.com | K18: Public
A19: SCHEDULE | B19: Saturday home games | C19: 11 | D19: 11 | E19: 12 | F19: 14 | G19: 10 | H19: 11 | I19: games | J19: Multiple official schedule releases on sandiegogulls.com | K19: Public/Projection
A20: SCHEDULE | B20: Sunday home games | C20: 1 | D20: 1 | E20: 2 | F20: 2 | G20: 5 | H20: 4 | I20: games | J20: Multiple official schedule releases on sandiegogulls.com | K20: Public/Projection
A21: SCHEDULE | B21: Back-to-back sets | C21: 24 | D21: 21 | E21: 18 | F21: 20 | G21: 22 | H21: 22 | I21: sets | J21: Multiple official schedule releases on sandiegogulls.com | K21: Public
A22: MARKETING | B22: Promotional/theme nights announced | C22: 13 | D22: 15 | E22: 16 | F22: 23 | G22: 28 | H22: 30 | I22: nights | J22: Multiple official promo releases on sandiegogulls.com | K22: Public/Projection
A23: MARKETING | B23: Giveaway items announced | C23: 7 | D23: 6 | E23: 10 | F23: 11 | G23: 5 | H23: 6 | I23: items | J23: Multiple official promo releases on sandiegogulls.com | K23: Public/Projection
A24: MARKETING | B24: Pregame tailgates | C24: 6 | D24: 6 | E24: 7 | F24: 7 | G24: 7 | H24: 8 | I24: events | J24: Multiple official promo releases on sandiegogulls.com | K24: Public/Projection
A25: TICKETING | B25: STM entry price | C25: 476 | D25: 540 | E25: 540 | F25: 560 | G25: 614 | H25: =ROUND(G25*(1+$H$10),0) -> 632 | I25: $/seat | J25: Multiple official ticketing releases on sandiegogulls.com | K25: Public/Projection
A26: TICKETING | B26: Single-game floor (box office / public) | C26: 19 | D26: 21 | E26: 20 | F26: 22 | G26: 23 | H26: =ROUND(G26*(1+$H$11),0) -> 24 | I26: $/ticket | J26: Multiple official ticketing releases on sandiegogulls.com | K26: Public/Estimate/Projection
A27: TICKETING | B27: Single-game floor (online incl. fees) | F27: 27.5 | G27: 28.75 | H27: 29.75 | I27: $/ticket | J27: https://www.sandiegogulls.com/news/detail/single-game-tickets-available-now | K27: Estimate/Projection
A28: TICKETING | B28: College ticket price | G28: 17 | H28: 17.5 | I28: $/ticket | J28: https://www.sandiegogulls.com/tickets/college | K28: Public/Projection
A29: TICKETING | B29: Family pack price floor | G29: 130 | H29: 135 | I29: $/pack | J29: https://www.sandiegogulls.com/tickets/4-packs | K29: Public/Projection
A30: TICKETING | B30: Group minimum size | C30: 10 | D30: 10 | E30: 10 | F30: 10 | G30: 10 | H30: 10 | I30: tickets | J30: https://www.sandiegogulls.com/tickets/group-tickets | K30: Public/Context
A31: TICKETING | B31: Max mini-plan discount | C31: 0.15 | D31: 0.15 | E31: 0.2 | F31: 0.3 | G31: 0.3 | H31: 0.3 | I31: pct | J31: https://www.sandiegogulls.com/tickets/gulls-mini-plans | K31: Estimate/Projection
A32: TICKETING | B32: Weighted average ticket price (modeled) | C32: 22 | D32: 22.4 | E32: 23.4 | F32: 24.4 | G32: 25.4 | H32: =ROUND(G32*(1+$H$6),2) -> 26.21 | I32: $/ticket | J32: Model methodology | K32: Estimate/Projection
A33: TICKETING | B33: Group sales share of gate | C33: 0.16 | D33: 0.17 | E33: 0.18 | F33: 0.19 | G33: 0.2 | H33: 0.21 | I33: pct | J33: Model methodology | K33: Estimate/Projection
A34: TICKETING | B34: Premium seating yield (included in gate) | C34: 380000 | D34: 400000 | E34: 460000 | F34: 520000 | G34: 600000 | H34: 660000 | I34: $ | J34: Model methodology | K34: Estimate/Projection
A35: TICKETING | B35: STM base (full-season equivalents) | C35: 2300 | D35: 2350 | E35: 2450 | F35: 2550 | G35: 2700 | H35: 2780 | I35: FSE | J35: Model methodology | K35: Estimate/Projection
A36: TICKETING | B36: STM retention rate | C36: 0.77 | D36: 0.76 | E36: 0.78 | F36: 0.8 | G36: 0.82 | H36: 0.83 | I36: pct | J36: Model methodology | K36: Estimate/Projection
A37: ANCILLARY | B37: F&B per-cap gross | C37: 13 | D37: 13.4 | E37: 14 | F37: 14.8 | G37: 15.5 | H37: =ROUND(G37*(1+$H$8),2) -> 16 | I37: $/attendee | J37: Model methodology | K37: Estimate/Projection
A38: ANCILLARY | B38: Team concession commission rate | C38: 0.04 | D38: 0.04 | E38: 0.04 | F38: 0.04 | G38: 0.04 | H38: 0.04 | I38: pct | J38: Model methodology | K38: Estimate
A39: ANCILLARY | B39: Merchandise per-cap | C39: 3.6 | D39: 3.8 | E39: 4 | F39: 4.2 | G39: 4.5 | H39: =ROUND(G39*(1+$H$9),2) -> 4.7 | I39: $/attendee | J39: Model methodology | K39: Estimate/Projection
A40: ANCILLARY | B40: Parking fee assumption | C40: 15 | D40: 15 | E40: 15 | F40: 18 | G40: 20 | H40: 21 | I40: $/vehicle | J40: https://pechangaarenasd.com/plan-your-visit/directions-parking/ | K40: Estimate/Projection
A41: ANCILLARY | B41: Average auto occupancy | C41: 2.6 | D41: 2.6 | E41: 2.6 | F41: 2.5 | G41: 2.5 | H41: 2.5 | I41: persons/vehicle | J41: Model methodology | K41: Estimate
A42: ANCILLARY | B42: Team share of parking | C42: 0.05 | D42: 0.05 | E42: 0.05 | F42: 0.05 | G42: 0.05 | H42: 0.05 | I42: pct | J42: Model methodology | K42: Estimate
A43: SPONSORSHIP | B43: Total sponsorship revenue | C43: 1950000 | D43: 2000000 | E43: 2200000 | F43: 2450000 | G43: 2700000 | H43: =ROUND(G43*(1+$H$7),0) -> 2951100 | I43: $ | J43: Model methodology | K43: Estimate/Projection
A44: SPONSORSHIP | B44: Title partner value | C44: 450000 | D44: 450000 | E44: 480000 | F44: 500000 | G44: 550000 | H44: 580000 | I44: $ | J44: Model methodology | K44: Estimate
A45: SPONSORSHIP | B45: Jersey / patch revenue | C45: 0 | D45: 0 | E45: 150000 | F45: 180000 | G45: 200000 | H45: 220000 | I45: $ | J45: Model methodology | K45: Estimate
A46: SPONSORSHIP | B46: Digital inventory yield | C46: 80000 | D46: 90000 | E46: 110000 | F46: 130000 | G46: 150000 | H46: 165000 | I46: $ | J46: Model methodology | K46: Estimate
A47: MEDIA | B47: Broadcast / streaming value | C47: 150000 | D47: 100000 | E47: 100000 | F47: 110000 | G47: 130000 | H47: 145000 | I47: $ | J47: https://theahl.com/news/ahl-flosports-partnership-extension | K47: Estimate
A48: DIGITAL | B48: Email subscribers (estimated active) | C48: 18000 | D48: 19000 | E48: 20000 | F48: 21000 | G48: 22000 | H48: 23000 | I48: subs | J48: Model methodology | K48: Estimate
A49: DIGITAL | B49: Social audience (aggregate est.) | C49: 150000 | D49: 165000 | E49: 180000 | F49: 195000 | G49: 205000 | H49: 215000 | I49: followers | J49: Multiple public social snippets | K49: Estimate
A50: DIGITAL | B50: Website monthly visits | C50: 28000 | D50: 29000 | E50: 31000 | F50: 33000 | G50: 35200 | H50: =ROUND(G50*(1+$H$12),0) -> 38016 | I50: visits | J50: https://www.similarweb.com/website/sandiegogulls.com/ | K50: Estimate/Projection
A51: DIGITAL | B51: Bounce rate | C51: 0.5 | D51: 0.495 | E51: 0.49 | F51: 0.48 | G51: 0.4725 | H51: 0.465 | I51: pct | J51: https://www.similarweb.com/website/sandiegogulls.com/ | K51: Estimate/Projection
A52: DIGITAL | B52: Pages per visit | C52: 1.55 | D52: 1.6 | E52: 1.65 | F52: 1.72 | G52: 1.8 | H52: 1.9 | I52: pages | J52: https://www.similarweb.com/website/sandiegogulls.com/ | K52: Estimate/Projection
A53: DIGITAL | B53: Average visit duration (sec) | C53: 60 | D53: 62 | E53: 65 | F53: 68 | G53: 70 | H53: 75 | I53: sec | J53: https://www.similarweb.com/website/sandiegogulls.com/ | K53: Estimate/Projection
A54: DIGITAL | B54: Organic search share | C54: 0.4 | D54: 0.41 | E54: 0.43 | F54: 0.44 | G54: 0.4551 | H54: 0.46 | I54: pct | J54: https://www.similarweb.com/website/sandiegogulls.com/ | K54: Estimate/Projection
A55: MARKETING | B55: Customer acquisition cost | C55: 45 | D55: 44 | E55: 42 | F55: 40 | G55: 39 | H55: 37 | I55: $/new buyer | J55: Model methodology | K55: Estimate
A56: MARKETING | B56: Net promoter score | C56: 45 | D56: 43 | E56: 46 | F56: 50 | G56: 54 | H56: 56 | I56: pts | J56: Model methodology | K56: Estimate
A57: ARENA | B57: Facility fee per paid ticket | E57: 2.5 | F57: 3 | G57: 3 | H57: 3 | I57: $/ticket | J57: Lease-era reporting / model assumption | K57: Estimate
A58: ARENA | B58: Base rent floor (annualized) | E58: 775716 | F58: 799107 | G58: 823084 | H58: 839546 | I58: $ | J58: https://www.lee-associates.com/elee/utc/newsletter/091224/article3.pdf | K58: Public/Projection
A59: ARENA | B59: Rent escalator | F59: 0.03 | G59: 0.03 | H59: 0.02 | I59: pct | J59: Lease-era reporting / model assumption | K59: Derived/Projection
A60: ARENA | B60: Security / police overhead per event | C60: 12000 | D60: 12000 | E60: 13000 | F60: 14000 | G60: 15000 | H60: 15500 | I60: $ | J60: https://www.sandiego.gov/sites/default/files/specialeventsopsmanual2020.pdf | K60: Estimate
A61: ARENA | B61: Utilities & HVAC load | C61: 180000 | D61: 190000 | E61: 210000 | F61: 230000 | G61: 250000 | H61: 260000 | I61: $ | J61: Model methodology | K61: Estimate
A62: ARENA | B62: Load-in / load-out allocation | C62: 80000 | D62: 85000 | E62: 90000 | F62: 95000 | G62: 100000 | H62: 105000 | I62: $ | J62: Model methodology | K62: Estimate
A63: ARENA | B63: Midway district assessment / CFD | C63: 0 | D63: 0 | E63: 0 | F63: 0 | G63: 0 | H63: 0 | I63: $ | J63: Public review | K63: Context
A64: ARENA | B64: Lease horizon (months remaining) | E64: 29 | F64: 17 | G64: 5 | H64: 0 | I64: months | J64: https://www.sandiego.gov/economic-development/real-estate/midway-rising | K64: Estimate
A65: ARENA | B65: Naming-rights tranche allocable to team ops | C65: 250000 | D65: 250000 | E65: 260000 | F65: 275000 | G65: 300000 | H65: 310000 | I65: $ | J65: Model methodology | K65: Estimate
A66: ARENA | B66: Tax liability | C66: 50000 | D66: 50000 | E66: 50000 | F66: 50000 | G66: 50000 | H66: 50000 | I66: $ | J66: Model methodology | K66: Estimate
A67: ARENA | B67: Debt-to-value ratio | C67: 0.05 | D67: 0.05 | E67: 0.05 | F67: 0.05 | G67: 0.05 | H67: 0.05 | I67: pct | J67: Model methodology | K67: Estimate
A68: HUMAN CAPITAL | B68: Roster headcount | C68: 22 | D68: 24 | E68: 26 | F68: 22 | G68: 29 | H68: 29 | I68: players | J68: Multiple official roster/game notes sources | K68: Public/Projection
A69: HUMAN CAPITAL | B69: Coaching staff payroll | C69: 550000 | D69: 560000 | E69: 580000 | F69: 620000 | G69: 680000 | H69: 710000 | I69: $ | J69: Model methodology | K69: Estimate
A70: HUMAN CAPITAL | B70: Front office FTE | C70: 42 | D70: 43 | E70: 44 | F70: 45 | G70: 46 | H70: 47 | I70: FTE | J70: https://www.linkedin.com/company/san-diego-gulls | K70: Estimate
A71: HUMAN CAPITAL | B71: Medical / training tech spend | C71: 100000 | D71: 110000 | E71: 130000 | F71: 150000 | G71: 175000 | H71: 185000 | I71: $ | J71: Model methodology | K71: Estimate
A72: HUMAN CAPITAL | B72: Travel logistics ratio (air-heavy) | C72: 0.82 | D72: 0.82 | E72: 0.83 | F72: 0.84 | G72: 0.84 | H72: 0.84 | I72: pct | J72: Model methodology | K72: Estimate
A73: HUMAN CAPITAL | B73: Player housing spend | C73: 200000 | D73: 210000 | E73: 230000 | F73: 250000 | G73: 280000 | H73: 290000 | I73: $ | J73: Model methodology | K73: Estimate
A74: HUMAN CAPITAL | B74: AHL-only salary floor | C74: 49000 | D74: 50000 | E74: 51500 | F74: 52725 | G74: 54000 | H74: 55620 | I74: $ | J74: https://phpa.com/site/agreements | K74: Estimate/Projection
A75: HUMAN CAPITAL | B75: AHL-only average salary | C75: 65000 | D75: 66000 | E75: 70000 | F75: 74000 | G75: 78000 | H75: 80000 | I75: $ | J75: Model methodology | K75: Estimate
A76: HUMAN CAPITAL | B76: Insurance premiums | C76: 200000 | D76: 210000 | E76: 230000 | F76: 250000 | G76: 270000 | H76: 280000 | I76: $ | J76: Model methodology | K76: Estimate
... A85: DIGITAL | B85: Email database value per active subscriber | C85: 5 | D85: 5 | E85: 5 | F85: 5 | G85: 5 | H85: 5 | I85: $/active sub | J85: Model control | K85: Control

Sheet Master_Model
A1: ID | B1: Group | C1: Field | D1: Unit | E1: 2021-22 | F1: 2022-23 | G1: 2023-24 | H1: 2024-25 | I1: 2025-26 | J1: 2026-27 | K1: Status | L1: Confidence | M1: Primary Source / Method | N1: Notes
A2: 1. Fan Demand, Schedule & Ticketing
A3: 1 | B3: Fan Demand / Ticketing | C3: Average attendance | D3: fans/game | E3: =Assumptions!C13 -> 6992 | F3: =Assumptions!D13 -> 6953 | G3: =Assumptions!E13 -> 7249 | H3: =Assumptions!F13 -> 7262 | I3: =Assumptions!G13 -> 7403 | J3: =Assumptions!H13 -> 7625 | K3: Public input / projection | L3: High | M3: HockeyDB / official schedule | N3: 2026-27 baseline projected from 2025-26 using control.
A4: 2 | B4: Fan Demand / Ticketing | C4: Home games | D4: games | E4: =Assumptions!C14 -> 34 | F4: =Assumptions!D14 -> 36 | G4: =Assumptions!E14 -> 36 | H4: =Assumptions!F14 -> 36 | I4: =Assumptions!G14 -> 36 | J4: =Assumptions!H14 -> 36 | K4: Public input | L4: High | M4: Official schedules | N4: 2021-22 was 34 home games; subsequent seasons 36.
A5: 3 | B5: Fan Demand / Ticketing | C5: Total home attendance | D5: fans | E5: =E3*E4 -> 237728 | F5: =F3*F4 -> 250308 | G5: =G3*G4 -> 260964 | H5: =H3*H4 -> 261432 | I5: =I3*I4 -> 266508 | J5: =J3*J4 -> 274500 | K5: Derived | L5: High | M5: Attendance × home games | N5: Average attendance multiplied by home games.
A6: 4 | B6: Fan Demand / Ticketing | C6: Home weekend dates | D6: dates | E6: =Assumptions!C17 -> 23 | F6: =Assumptions!D17 -> 23 | G6: =Assumptions!E17 -> 26 | H6: =Assumptions!F17 -> 25 | I6: =Assumptions!G17 -> 25 | J6: =Assumptions!H17 -> 25 | K6: Public input | L6: High | M6: Official schedules | N6: Official yearly schedule releases.
A7: 5 | B7: Fan Demand / Ticketing | C7: Friday home games | D7: games | E7: =Assumptions!C18 -> 11 | F7: =Assumptions!D18 -> 12 | G7: =Assumptions!E18 -> 12 | H7: =Assumptions!F18 -> 9 | I7: =Assumptions!G18 -> 10 | J7: =Assumptions!H18 -> 10 | K7: Public input | L7: High | M7: Official schedules | N7: Official yearly schedule releases.
A8: 6 | B8: Fan Demand / Ticketing | C8: Saturday home games | D8: games | E8: =Assumptions!C19 -> 11 | F8: =Assumptions!D19 -> 11 | G8: =Assumptions!E19 -> 12 | H8: =Assumptions!F19 -> 14 | I8: =Assumptions!G19 -> 10 | J8: =Assumptions!H19 -> 11 | K8: Public input / projection | L8: High | M8: Official schedules | N8: 2026-27 baseline projected mix.
A9: 7 | B9: Fan Demand / Ticketing | C9: Sunday home games | D9: games | E9: =Assumptions!C20 -> 1 | F9: =Assumptions!D20 -> 1 | G9: =Assumptions!E20 -> 2 | H9: =Assumptions!F20 -> 2 | I9: =Assumptions!G20 -> 5 | J9: =Assumptions!H20 -> 4 | K9: Public input / projection | L9: High | M9: Official schedules | N9: 2026-27 baseline projected mix.
A10: 8 | B10: Fan Demand / Ticketing | C10: Back-to-back sets | D10: sets | E10: =Assumptions!C21 -> 24 | F10: =Assumptions!D21 -> 21 | G10: =Assumptions!E21 -> 18 | H10: =Assumptions!F21 -> 20 | I10: =Assumptions!G21 -> 22 | J10: =Assumptions!H21 -> 22 | K10: Public input | L10: High | M10: Official schedules | N10: Official yearly schedule releases.
A11: 9 | B11: Fan Demand / Ticketing | C11: Promotional / theme nights | D11: nights | E11: =Assumptions!C22 -> 13 | F11: =Assumptions!D22 -> 15 | G11: =Assumptions!E22 -> 16 | H11: =Assumptions!F22 -> 23 | I11: =Assumptions!G22 -> 28 | J11: =Assumptions!H22 -> 30 | K11: Public input / projection | L11: High | M11: Official promo releases | N11: 2025-26 includes 8 anniversary nights + 20 additional promotional nights.
A12: 10 | B12: Fan Demand / Ticketing | C12: Giveaway items | D12: items | E12: =Assumptions!C23 -> 7 | F12: =Assumptions!D23 -> 6 | G12: =Assumptions!E23 -> 10 | H12: =Assumptions!F23 -> 11 | I12: =Assumptions!G23 -> 5 | J12: =Assumptions!H23 -> 6 | K12: Public input / projection | L12: Medium | M12: Official promo releases | N12: 2025-26 current public list includes five announced giveaways.
A13: 11 | B13: Fan Demand / Ticketing | C13: Pregame tailgates | D13: events | E13: =Assumptions!C24 -> 6 | F13: =Assumptions!D24 -> 6 | G13: =Assumptions!E24 -> 7 | H13: =Assumptions!F24 -> 7 | I13: =Assumptions!G24 -> 7 | J13: =Assumptions!H24 -> 8 | K13: Public input / projection | L13: Medium | M13: Official promo releases | N13: Counted / projected from public promo schedules.
A14: 12 | B14: Fan Demand / Ticketing | C14: STM entry price | D14: $ | E14: =Assumptions!C25 -> 476 | F14: =Assumptions!D25 -> 540 | G14: =Assumptions!E25 -> 540 | H14: =Assumptions!F25 -> 560 | I14: =Assumptions!G25 -> 614 | J14: =Assumptions!H25 -> 632 | K14: Public input / projection | L14: High | M14: Official ticketing releases | N14: Gulls Elite floor price.
A15: 13 | B15: Fan Demand / Ticketing | C15: STM entry price per game | D15: $ | E15: =E14/E4 -> 14 | F15: =F14/F4 -> 15 | G15: =G14/G4 -> 15 | H15: =H14/H4 -> 15.555556 | I15: =I14/I4 -> 17.055556 | J15: =J14/J4 -> 17.555556 | K15: Derived | L15: High | M15: STM entry price ÷ home games | N15: Season-ticket floor divided by home games.
A16: 14 | B16: Fan Demand / Ticketing | C16: Single-game floor (box office / public) | D16: $ | E16: =Assumptions!C26 -> 19 | F16: =Assumptions!D26 -> 21 | G16: =Assumptions!E26 -> 20 | H16: =Assumptions!F26 -> 22 | I16: =Assumptions!G26 -> 23 | J16: =Assumptions!H26 -> 24 | K16: Public input / estimate / projection | L16: Medium | M16: Official ticketing releases | N16: 2024-25 floor is interpolated estimate.
A17: 15 | B17: Fan Demand / Ticketing | C17: Single-game floor (online incl. fees) | D17: $ | E17: =Assumptions!C27 -> 0 | F17: =Assumptions!D27 -> 0 | G17: =Assumptions!E27 -> 0 | H17: =Assumptions!F27 -> 27.5 | I17: =Assumptions!G27 -> 28.75 | J17: =Assumptions!H27 -> 29.75 | K17: Estimate / projection | L17: Medium | M17: Official 2025-26 ticketing release | N17: 2025-26 is official; 2024-25 and 2026-27 are modeled estimates.
A18: 16 | B18: Fan Demand / Ticketing | C18: College ticket price | D18: $ | E18: =Assumptions!C28 -> 0 | F18: =Assumptions!D28 -> 0 | G18: =Assumptions!E28 -> 0 | H18: =Assumptions!F28 -> 0 | I18: =Assumptions!G28 -> 17 | J18: =Assumptions!H28 -> 17.5 | K18: Public input / projection | L18: Medium | M18: Official college page | N18: Current season official price.
A19: 17 | B19: Fan Demand / Ticketing | C19: Family pack price floor | D19: $ | E19: =Assumptions!C29 -> 0 | F19: =Assumptions!D29 -> 0 | G19: =Assumptions!E29 -> 0 | H19: =Assumptions!F29 -> 0 | I19: =Assumptions!G29 -> 130 | J19: =Assumptions!H29 -> 135 | K19: Public input / projection | L19: Medium | M19: Official family-pack page | N19: Current-season official product.
A20: 18 | B20: Fan Demand / Ticketing | C20: Group minimum size | D20: tickets | E20: =Assumptions!C30 -> 10 | F20: =Assumptions!D30 -> 10 | G20: =Assumptions!E30 -> 10 | H20: =Assumptions!F30 -> 10 | I20: =Assumptions!G30 -> 10 | J20: =Assumptions!H30 -> 10 | K20: Public / context | L20: Medium | M20: Official group page | N20: Assumed stable historically.
A21: 19 | B21: Fan Demand / Ticketing | C21: Max mini-plan discount | D21: pct | E21: =Assumptions!C31 -> 0.15 | F21: =Assumptions!D31 -> 0.15 | G21: =Assumptions!E31 -> 0.2 | H21: =Assumptions!F31 -> 0.3 | I21: =Assumptions!G31 -> 0.3 | J21: =Assumptions!H31 -> 0.3 | K21: Estimate / projection | L21: Low | M21: Public current mini-plan page | N21: Historical values are conservative placeholders.
A22: 20 | B22: Fan Demand / Ticketing | C22: Weighted average ticket price (modeled) | D22: $ | E22: =Assumptions!C32 -> 22 | F22: =Assumptions!D32 -> 22.4 | G22: =Assumptions!E32 -> 23.4 | H22: =Assumptions!F32 -> 24.4 | I22: =Assumptions!G32 -> 25.4 | J22: =Assumptions!H32 -> 26.21 | K22: Estimate / projection | L22: Medium | M22: Model methodology | N22: Modeled from ticket product mix and public price anchors.
A23: 21 | B23: Fan Demand / Ticketing | C23: Group sales share of gate | D23: pct | E23: =Assumptions!C33 -> 0.16 | F23: =Assumptions!D33 -> 0.17 | G23: =Assumptions!E33 -> 0.18 | H23: =Assumptions!F33 -> 0.19 | I23: =Assumptions!G33 -> 0.2 | J23: =Assumptions!H33 -> 0.21 | K23: Estimate / projection | L23: Low | M23: Model methodology | N23: Logical range based on minor-league group channel importance.
A24: 22 | B24: Fan Demand / Ticketing | C24: Premium seating yield | D24: $ | E24: =Assumptions!C34 -> 380000 | F24: =Assumptions!D34 -> 400000 | G24: =Assumptions!E34 -> 460000 | H24: =Assumptions!F34 -> 520000 | I24: =Assumptions!G34 -> 600000 | J24: =Assumptions!H34 -> 660000 | K24: Estimate / projection | L24: Low | M24: Model methodology | N24: Embedded within gate yield; not additive in revenue total.
A25: 23 | B25: Fan Demand / Ticketing | C25: STM base (FSE) | D25: FSE | E25: =Assumptions!C35 -> 2300 | F25: =Assumptions!D35 -> 2350 | G25: =Assumptions!E35 -> 2450 | H25: =Assumptions!F35 -> 2550 | I25: =Assumptions!G35 -> 2700 | J25: =Assumptions!H35 -> 2780 | K25: Estimate / projection | L25: Low | M25: Model methodology | N25: Modeled from attendance and ticket mix.
A26: 24 | B26: Fan Demand / Ticketing | C26: STM retention rate | D26: pct | E26: =Assumptions!C36 -> 0.77 | F26: =Assumptions!D36 -> 0.76 | G26: =Assumptions!E36 -> 0.78 | H26: =Assumptions!F36 -> 0.8 | I26: =Assumptions!G36 -> 0.82 | J26: =Assumptions!H36 -> 0.83 | K26: Estimate / projection | L26: Low | M26: Model methodology | N26: Modeled range.
A27: 2. Revenue Engine & Economics
A28: 25 | B28: Revenue Engine | C28: Gate revenue | D28: $ | E28: =E5*E22 -> 5230016 | F28: =F5*F22 -> 5606899.2 | G28: =G5*G22 -> 6106557.6 | H28: =H5*H22 -> 6378940.8 | I28: =I5*I22 -> 6769303.2 | J28: =J5*J22 -> 7194645 | K28: Derived | L28: Medium | M28: Total attendance × WATP | N28: Modeled gate revenue using weighted average ticket price.
A29: 26 | B29: Revenue Engine | C29: Facility fee per paid ticket | D29: $ | E29: =Assumptions!C57 -> 0 | F29: =Assumptions!D57 -> 0 | G29: =Assumptions!E57 -> 2.5 | H29: =Assumptions!F57 -> 3 | I29: =Assumptions!G57 -> 3 | J29: =Assumptions!H57 -> 3 | K29: Estimate | L29: Low | M29: Lease-era reporting / model assumption | N29: Publicly discussed current surcharge structure; early years not confirmed.
A30: 27 | B30: Revenue Engine | C30: Facility fee liability | D30: $ | E30: =IFERROR(E5*E29,"") -> 0 | F30: =IFERROR(F5*F29,"") -> 0 | G30: =IFERROR(G5*G29,"") -> 652410 | H30: =IFERROR(H5*H29,"") -> 784296 | I30: =IFERROR(I5*I29,"") -> 799524 | J30: =IFERROR(J5*J29,"") -> 823500 | K30: Derived | L30: Low | M30: Total attendance × facility fee | N30: Pass-through city/venue fee liability estimate.
A31: 28 | B31: Revenue Engine | C31: Revenue per available seat (RevPAS) | D31: $ | E31: =IFERROR(E28/(E53*E4),"") -> 11.905882 | F31: =IFERROR(F28/(F53*F4),"") -> 12.054737 | G31: =IFERROR(G28/(G53*G4),"") -> 13.128994 | H31: =IFERROR(H28/(H53*H4),"") -> 13.714613 | I31: =IFERROR(I28/(I53*I4),"") -> 14.553885 | J31: =IFERROR(J28/(J53*J4),"") -> 15.468363 | K31: Derived | L31: Medium | M31: Gate ÷ (capacity × home games) | N31: Uses 12,920 hockey capacity.
A32: 29 | B32: Revenue Engine | C32: F&B per-cap gross | D32: $ | E32: =Assumptions!C37 -> 13 | F32: =Assumptions!D37 -> 13.4 | G32: =Assumptions!E37 -> 14 | H32: =Assumptions!F37 -> 14.8 | I32: =Assumptions!G37 -> 15.5 | J32: =Assumptions!H37 -> 16 | K32: Estimate / projection | L32: Low | M32: Model methodology | N32: Gross in-building spend, not team net.
A33: 30 | B33: Revenue Engine | C33: Team concession commission rate | D33: pct | E33: =Assumptions!C38 -> 0.04 | F33: =Assumptions!D38 -> 0.04 | G33: =Assumptions!E38 -> 0.04 | H33: =Assumptions!F38 -> 0.04 | I33: =Assumptions!G38 -> 0.04 | J33: =Assumptions!H38 -> 0.04 | K33: Estimate | L33: Low | M33: Model methodology | N33: Private split; modeled nominal rate.
A34: 31 | B34: Revenue Engine | C34: Concession commission revenue | D34: $ | E34: =E5*E32*E33 -> 123618.56 | F34: =F5*F32*F33 -> 134165.09 | G34: =G5*G32*G33 -> 146139.84 | H34: =H5*H32*H33 -> 154767.74 | I34: =I5*I32*I33 -> 165234.96 | J34: =J5*J32*J33 -> 175680 | K34: Derived | L34: Low | M34: Attendance × F&B per-cap × commission rate | N34: Team-side concession revenue estimate.
A35: 32 | B35: Revenue Engine | C35: Merchandise per-cap | D35: $ | E35: =Assumptions!C39 -> 3.6 | F35: =Assumptions!D39 -> 3.8 | G35: =Assumptions!E39 -> 4 | H35: =Assumptions!F39 -> 4.2 | I35: =Assumptions!G39 -> 4.5 | J35: =Assumptions!H39 -> 4.7 | K35: Estimate / projection | L35: Low | M35: Model methodology | N35: Modeled team-store spend per attendee.
A36: 33 | B36: Revenue Engine | C36: Merchandise revenue | D36: $ | E36: =E5*E35 -> 855820.8 | F36: =F5*F35 -> 951170.4 | G36: =G5*G35 -> 1043856 | H36: =H5*H35 -> 1098014.4 | I36: =I5*I35 -> 1199286 | J36: =J5*J35 -> 1290150 | K36: Derived | L36: Low | M36: Attendance × merch per-cap | N36: Modeled gross merchandise revenue.
A37: 34 | B37: Revenue Engine | C37: Parking fee assumption | D37: $ | E37: =Assumptions!C40 -> 15 | F37: =Assumptions!D40 -> 15 | G37: =Assumptions!E40 -> 15 | H37: =Assumptions!F40 -> 18 | I37: =Assumptions!G40 -> 20 | J37: =Assumptions!H40 -> 21 | K37: Estimate / projection | L37: Low | M37: Public parking page + model | N37: Event-specific public fee structure; year values are model anchors.
A38: 35 | B38: Revenue Engine | C38: Average auto occupancy | D38: persons | E38: =Assumptions!C41 -> 2.6 | F38: =Assumptions!D41 -> 2.6 | G38: =Assumptions!E41 -> 2.6 | H38: =Assumptions!F41 -> 2.5 | I38: =Assumptions!G41 -> 2.5 | J38: =Assumptions!H41 -> 2.5 | K38: Estimate | L38: Low | M38: Model methodology | N38: Transport assumption for parking yield.
A39: 36 | B39: Revenue Engine | C39: Team share of parking | D39: pct | E39: =Assumptions!C42 -> 0.05 | F39: =Assumptions!D42 -> 0.05 | G39: =Assumptions!E42 -> 0.05 | H39: =Assumptions!F42 -> 0.05 | I39: =Assumptions!G42 -> 0.05 | J39: =Assumptions!H42 -> 0.05 | K39: Estimate | L39: Low | M39: Model methodology | N39: No public split located; nominal placeholder only.
A40: 37 | B40: Revenue Engine | C40: Parking revenue yield | D40: $ | E40: =IFERROR((E5/E38)*E37*E39,"") -> 68575.385 | F40: =IFERROR((F5/F38)*F37*F39,"") -> 72204.231 | G40: =IFERROR((G5/G38)*G37*G39,"") -> 75278.077 | H40: =IFERROR((H5/H38)*H37*H39,"") -> 94115.52 | I40: =IFERROR((I5/I38)*I37*I39,"") -> 106603.2 | J40: =IFERROR((J5/J38)*J37*J39,"") -> 115290 | K40: Derived | L40: Low | M40: Attendance ÷ occupancy × fee × share | N40: Team-side parking estimate.
A41: 38 | B41: Revenue Engine | C41: Total per-cap spend (F&B + merch) | D41: $ | E41: =E32+E35 -> 16.6 | F41: =F32+F35 -> 17.2 | G41: =G32+G35 -> 18 | H41: =H32+H35 -> 19 | I41: =I32+I35 -> 20 | J41: =J32+J35 -> 20.7 | K41: Derived | L41: Low | M41: F&B per-cap + merch per-cap | N41: Gross fan spend indicator.
A42: 39 | B42: Revenue Engine | C42: Total sponsorship revenue | D42: $ | E42: =Assumptions!C43 -> 1950000 | F42: =Assumptions!D43 -> 2000000 | G42: =Assumptions!E43 -> 2200000 | H42: =Assumptions!F43 -> 2450000 | I42: =Assumptions!G43 -> 2700000 | J42: =Assumptions!H43 -> 2951100 | K42: Estimate / projection | L42: Low | M42: Model methodology | N42: Total sponsorship / partner inventory revenue.
A43: 40 | B43: Revenue Engine | C43: Title partner value | D43: $ | E43: =Assumptions!C44 -> 450000 | F43: =Assumptions!D44 -> 450000 | G43: =Assumptions!E44 -> 480000 | H43: =Assumptions!F44 -> 500000 | I43: =Assumptions!G44 -> 550000 | J43: =Assumptions!H44 -> 580000 | K43: Estimate | L43: Low | M43: Model methodology | N43: Subcomponent of sponsorship total.
A44: 41 | B44: Revenue Engine | C44: Jersey / patch revenue | D44: $ | E44: =Assumptions!C45 -> 0 | F44: =Assumptions!D45 -> 0 | G44: =Assumptions!E45 -> 150000 | H44: =Assumptions!F45 -> 180000 | I44: =Assumptions!G45 -> 200000 | J44: =Assumptions!H45 -> 220000 | K44: Estimate | L44: Low | M44: Model methodology | N44: Subcomponent of sponsorship total.
A45: 42 | B45: Revenue Engine | C45: Digital inventory yield | D45: $ | E45: =Assumptions!C46 -> 80000 | F45: =Assumptions!D46 -> 90000 | G45: =Assumptions!E46 -> 110000 | H45: =Assumptions!F46 -> 130000 | I45: =Assumptions!G46 -> 150000 | J45: =Assumptions!H46 -> 165000 | K45: Estimate | L45: Low | M45: Model methodology | N45: Subcomponent of sponsorship total.
A46: 43 | B46: Revenue Engine | C46: Other sponsorship revenue | D46: $ | E46: =E42-E43-E44-E45 -> 1420000 | F46: =F42-F43-F44-F45 -> 1460000 | G46: =G42-G43-G44-G45 -> 1460000 | H46: =H42-H43-H44-H45 -> 1640000 | I46: =I42-I43-I44-I45 -> 1800000 | J46: =J42-J43-J44-J45 -> 1986100 | K46: Derived | L46: Low | M46: Residual sponsorship value | N46: Total sponsorship less title, patch, and digital subcomponents.
A47: 44 | B47: Revenue Engine | C47: Broadcast / streaming value | D47: $ | E47: =Assumptions!C47 -> 150000 | F47: =Assumptions!D47 -> 100000 | G47: =Assumptions!E47 -> 100000 | H47: =Assumptions!F47 -> 110000 | I47: =Assumptions!G47 -> 130000 | J47: =Assumptions!H47 -> 145000 | K47: Estimate | L47: Low | M47: AHL/FloHockey + local TV context | N47: Modeled media value.
A48: 45 | B48: Revenue Engine | C48: Youth hockey / camp revenue | D48: $ | E48: =Assumptions!C80 -> 80000 | F48: =Assumptions!D80 -> 90000 | G48: =Assumptions!E80 -> 100000 | H48: =Assumptions!F80 -> 120000 | I48: =Assumptions!G80 -> 140000 | J48: =Assumptions!H80 -> 160000 | K48: Estimate | L48: Low | M48: Model methodology | N48: Direct ecosystem youth / camp estimate.
A49: 46 | B49: Revenue Engine | C49: Gross annual revenue | D49: $ | E49: =E28+E34+E36+E40+E42+E47+E48 -> 8458030.7 | F49: =F28+F34+F36+F40+F42+F47+F48 -> 8954438.9 | G49: =G28+G34+G36+G40+G42+G47+G48 -> 9771831.5 | H49: =H28+H34+H36+H40+H42+H47+H48 -> 10405838 | I49: =I28+I34+I36+I40+I42+I47+I48 -> 11210427 | J49: =J28+J34+J36+J40+J42+J47+J48 -> 12031865 | K49: Derived | L49: Medium | M49: Gate + commission + merch + parking + sponsorship + media + youth | N49: Excludes NHL parent subsidy to preserve stand-alone club revenue view.
A50: 47 | B50: Revenue Engine | C50: NHL parent subsidy | D50: $ | E50: =Assumptions!C79 -> 4200000 | F50: =Assumptions!D79 -> 4300000 | G50: =Assumptions!E79 -> 4400000 | H50: =Assumptions!F79 -> 4500000 | I50: =Assumptions!G79 -> 4700000 | J50: =Assumptions!H79 -> 4900000 | K50: Estimate | L50: Low | M50: Model methodology | N50: Anaheim Ducks affiliate support estimate.
A51: 48 | B51: Revenue Engine | C51: Operating resources incl. parent support | D51: $ | E51: =E49+E50 -> 12658031 | F51: =F49+F50 -> 13254439 | G51: =G49+G50 -> 14171832 | H51: =H49+H50 -> 14905838 | I51: =I49+I50 -> 15910427 | J51: =J49+J50 -> 16931865 | K51: Derived | L51: Low | M51: Gross revenue + parent subsidy | N51: Useful for full operating-scale context.
A52: 3. Arena, Municipal & Venue Footprint
A53: 49 | B53: Arena / Municipal | C53: Hockey seating capacity | D53: seats | E53: =Assumptions!C15 -> 12920 | F53: =Assumptions!D15 -> 12920 | G53: =Assumptions!E15 -> 12920 | H53: =Assumptions!F15 -> 12920 | I53: =Assumptions!G15 -> 12920 | J53: =Assumptions!H15 -> 12920 | K53: Context | L53: Medium | M53: Official media guide | N53: Capacity used in RevPAS.
A54: 50 | B54: Arena / Municipal | C54: General venue capacity | D54: seats | E54: =Assumptions!C16 -> 14000 | F54: =Assumptions!D16 -> 14000 | G54: =Assumptions!E16 -> 14000 | H54: =Assumptions!F16 -> 14000 | I54: =Assumptions!G16 -> 14000 | J54: =Assumptions!H16 -> 14000 | K54: Public | L54: High | M54: Official venue page | N54: Current listed arena capacity.
A55: 51 | B55: Arena / Municipal | C55: Base rent floor (annualized) | D55: $ | E55: =Assumptions!C58 -> 0 | F55: =Assumptions!D58 -> 0 | G55: =Assumptions!E58 -> 775716 | H55: =Assumptions!F58 -> 799107 | I55: =Assumptions!G58 -> 823084 | J55: =Assumptions!H58 -> 839546 | K55: Public / projection | L55: Medium | M55: Arena lease reporting | N55: Arena-operator level, not disclosed team sublease.
A56: 52 | B56: Arena / Municipal | C56: Rent escalator | D56: pct | E56: =Assumptions!C59 -> 0 | F56: =Assumptions!D59 -> 0 | G56: =Assumptions!E59 -> 0 | H56: =Assumptions!F59 -> 0.03 | I56: =Assumptions!G59 -> 0.03 | J56: =Assumptions!H59 -> 0.02 | K56: Derived / projection | L56: Medium | M56: Lease floor progression | N56: Derived from public operator-level rent floor.
A57: 53 | B57: Arena / Municipal | C57: Security / police overhead per event | D57: $ | E57: =Assumptions!C60 -> 12000 | F57: =Assumptions!D60 -> 12000 | G57: =Assumptions!E60 -> 13000 | H57: =Assumptions!F60 -> 14000 | I57: =Assumptions!G60 -> 15000 | J57: =Assumptions!H60 -> 15500 | K57: Estimate | L57: Low | M57: City event policing framework | N57: Event cost estimate.
A58: 54 | B58: Arena / Municipal | C58: Security / police overhead (annual) | D58: $ | E58: =E57*E4 -> 408000 | F58: =F57*F4 -> 432000 | G58: =G57*G4 -> 468000 | H58: =H57*H4 -> 504000 | I58: =I57*I4 -> 540000 | J58: =J57*J4 -> 558000 | K58: Derived | L58: Low | M58: Per-event security × home games | N58: Annualized event security cost.
A59: 55 | B59: Arena / Municipal | C59: Utilities & HVAC load | D59: $ | E59: =Assumptions!C61 -> 180000 | F59: =Assumptions!D61 -> 190000 | G59: =Assumptions!E61 -> 210000 | H59: =Assumptions!F61 -> 230000 | I59: =Assumptions!G61 -> 250000 | J59: =Assumptions!H61 -> 260000 | K59: Estimate | L59: Low | M59: Model methodology | N59: Annualized utilities / ice / cooling.
A60: 56 | B60: Arena / Municipal | C60: Load-in / load-out allocation | D60: $ | E60: =Assumptions!C62 -> 80000 | F60: =Assumptions!D62 -> 85000 | G60: =Assumptions!E62 -> 90000 | H60: =Assumptions!F62 -> 95000 | I60: =Assumptions!G62 -> 100000 | J60: =Assumptions!H62 -> 105000 | K60: Estimate | L60: Low | M60: Model methodology | N60: Annualized mixed-use arena conversion allocation.
A61: 57 | B61: Arena / Municipal | C61: Midway district assessment / CFD | D61: $ | E61: =Assumptions!C63 -> 0 | F61: =Assumptions!D63 -> 0 | G61: =Assumptions!E63 -> 0 | H61: =Assumptions!F63 -> 0 | I61: =Assumptions!G63 -> 0 | J61: =Assumptions!H63 -> 0 | K61: Context | L61: Low | M61: Public review | N61: No public team-side assessment identified.
A62: 58 | B62: Arena / Municipal | C62: Lease horizon (months remaining) | D62: months | E62: =Assumptions!C64 -> 0 | F62: =Assumptions!D64 -> 0 | G62: =Assumptions!E64 -> 29 | H62: =Assumptions!F64 -> 17 | I62: =Assumptions!G64 -> 5 | J62: =Assumptions!H64 -> 0 | K62: Estimate | L62: Low | M62: Midway Rising timeline | N62: Directional planning metric only.
A63: 59 | B63: Arena / Municipal | C63: Naming-rights tranche allocable to team ops | D63: $ | E63: =Assumptions!C65 -> 250000 | F63: =Assumptions!D65 -> 250000 | G63: =Assumptions!E65 -> 260000 | H63: =Assumptions!F65 -> 275000 | I63: =Assumptions!G65 -> 300000 | J63: =Assumptions!H65 -> 310000 | K63: Estimate | L63: Low | M63: Model methodology | N63: Logical annual value attributed to team ops.
A64: 60 | B64: Arena / Municipal | C64: Tax liability | D64: $ | E64: =Assumptions!C66 -> 50000 | F64: =Assumptions!D66 -> 50000 | G64: =Assumptions!E66 -> 50000 | H64: =Assumptions!F66 -> 50000 | I64: =Assumptions!G66 -> 50000 | J64: =Assumptions!H66 -> 50000 | K64: Estimate | L64: Low | M64: Model methodology | N64: Nominal local tax placeholder.
A65: 61 | B65: Arena / Municipal | C65: Debt-to-value ratio | D65: pct | E65: =Assumptions!C67 -> 0.05 | F65: =Assumptions!D67 -> 0.05 | G65: =Assumptions!E67 -> 0.05 | H65: =Assumptions!F67 -> 0.05 | I65: =Assumptions!G67 -> 0.05 | J65: =Assumptions!H67 -> 0.05 | K65: Estimate | L65: Low | M65: Model methodology | N65: Nominal placeholder only.
A66: 4. Hockey Ops, Organization & Human Capital
A67: 62 | B67: Human Capital | C67: Roster headcount | D67: players | E67: =Assumptions!C68 -> 22 | F67: =Assumptions!D68 -> 24 | G67: =Assumptions!E68 -> 26 | H67: =Assumptions!F68 -> 22 | I67: =Assumptions!G68 -> 29 | J67: =Assumptions!H68 -> 29 | K67: Public / projection | L67: Medium | M67: Official roster / game notes | N67: Opening-night/current roster anchor.
A68: 63 | B68: Human Capital | C68: Coaching staff payroll | D68: $ | E68: =Assumptions!C69 -> 550000 | F68: =Assumptions!D69 -> 560000 | G68: =Assumptions!E69 -> 580000 | H68: =Assumptions!F69 -> 620000 | I68: =Assumptions!G69 -> 680000 | J68: =Assumptions!H69 -> 710000 | K68: Estimate | L68: Low | M68: Model methodology | N68: Head coach + assistants + video support.
A69: 64 | B69: Human Capital | C69: Front office FTE | D69: FTE | E69: =Assumptions!C70 -> 42 | F69: =Assumptions!D70 -> 43 | G69: =Assumptions!E70 -> 44 | H69: =Assumptions!F70 -> 45 | I69: =Assumptions!G70 -> 46 | J69: =Assumptions!H70 -> 47 | K69: Estimate | L69: Medium | M69: Official front office + LinkedIn | N69: Business / marketing / partnership staff estimate.
A70: 65 | B70: Human Capital | C70: Medical / training tech spend | D70: $ | E70: =Assumptions!C71 -> 100000 | F70: =Assumptions!D71 -> 110000 | G70: =Assumptions!E71 -> 130000 | H70: =Assumptions!F71 -> 150000 | I70: =Assumptions!G71 -> 175000 | J70: =Assumptions!H71 -> 185000 | K70: Estimate | L70: Low | M70: Model methodology | N70: Sports science / recovery allocation.
A71: 66 | B71: Human Capital | C71: Travel logistics ratio (air-heavy) | D71: pct | E71: =Assumptions!C72 -> 0.82 | F71: =Assumptions!D72 -> 0.82 | G71: =Assumptions!E72 -> 0.83 | H71: =Assumptions!F72 -> 0.84 | I71: =Assumptions!G72 -> 0.84 | J71: =Assumptions!H72 -> 0.84 | K71: Estimate | L71: Low | M71: Model methodology | N71: Travel intensity ratio.
A72: 67 | B72: Human Capital | C72: Player housing spend | D72: $ | E72: =Assumptions!C73 -> 200000 | F72: =Assumptions!D73 -> 210000 | G72: =Assumptions!E73 -> 230000 | H72: =Assumptions!F73 -> 250000 | I72: =Assumptions!G73 -> 280000 | J72: =Assumptions!H73 -> 290000 | K72: Estimate | L72: Low | M72: Model methodology | N72: Local market housing support estimate.
A73: 68 | B73: Human Capital | C73: AHL-only salary floor | D73: $ | E73: =Assumptions!C74 -> 49000 | F73: =Assumptions!D74 -> 50000 | G73: =Assumptions!E74 -> 51500 | H73: =Assumptions!F74 -> 52725 | I73: =Assumptions!G74 -> 54000 | J73: =Assumptions!H74 -> 55620 | K73: Estimate / projection | L73: Medium | M73: PHPA / benchmark | N73: 2024-25 visible minimum, other years stepped.
A74: 69 | B74: Human Capital | C74: AHL-only average salary | D74: $ | E74: =Assumptions!C75 -> 65000 | F74: =Assumptions!D75 -> 66000 | G74: =Assumptions!E75 -> 70000 | H74: =Assumptions!F75 -> 74000 | I74: =Assumptions!G75 -> 78000 | J74: =Assumptions!H75 -> 80000 | K74: Estimate | L74: Low | M74: Model methodology | N74: Modeled non-NHL salary average.
A75: 70 | B75: Human Capital | C75: Insurance premiums | D75: $ | E75: =Assumptions!C76 -> 200000 | F75: =Assumptions!D76 -> 210000 | G75: =Assumptions!E76 -> 230000 | H75: =Assumptions!F76 -> 250000 | I75: =Assumptions!G76 -> 270000 | J75: =Assumptions!H76 -> 280000 | K75: Estimate | L75: Low | M75: Model methodology | N75: Workers' comp / liability allocation.
A76: 71 | B76: Human Capital | C76: Equipment lifecycle cost | D76: $ | E76: =Assumptions!C77 -> 150000 | F76: =Assumptions!D77 -> 155000 | G76: =Assumptions!E77 -> 165000 | H76: =Assumptions!F77 -> 175000 | I76: =Assumptions!G77 -> 190000 | J76: =Assumptions!H77 -> 195000 | K76: Estimate | L76: Low | M76: Model methodology | N76: Annual equipment budget estimate.
A77: 72 | B77: Human Capital | C77: Ducks prospects in San Diego | D77: players | E77: =Assumptions!C78 -> 8 | F77: =Assumptions!D78 -> 8 | G77: =Assumptions!E78 -> 9 | H77: =Assumptions!F78 -> 9 | I77: =Assumptions!G78 -> 15 | J77: =Assumptions!H78 -> 15 | K77: Estimate | L77: Low | M77: Official roster/game notes | N77: Approximate Ducks-controlled development pipeline.
A78: 5. Digital, Marketing & Brand Equity
A79: 73 | B79: Digital / Brand | C79: Email subscribers (estimated active) | D79: subs | E79: =Assumptions!C48 -> 18000 | F79: =Assumptions!D48 -> 19000 | G79: =Assumptions!E48 -> 20000 | H79: =Assumptions!F48 -> 21000 | I79: =Assumptions!G48 -> 22000 | J79: =Assumptions!H48 -> 23000 | K79: Estimate | L79: Low | M79: Model methodology | N79: Owned-contact base estimate.
A80: 74 | B80: Digital / Brand | C80: Email database value per active subscriber | D80: $ | E80: =Assumptions!C85 -> 5 | F80: =Assumptions!D85 -> 5 | G80: =Assumptions!E85 -> 5 | H80: =Assumptions!F85 -> 5 | I80: =Assumptions!G85 -> 5 | J80: =Assumptions!H85 -> 5 | K80: Control | L80: Medium | M80: User assumption | N80: User-directed valuation heuristic.
A81: 75 | B81: Digital / Brand | C81: Email database value | D81: $ | E81: =E79*E80 -> 90000 | F81: =F79*F80 -> 95000 | G81: =G79*G80 -> 100000 | H81: =H79*H80 -> 105000 | I81: =I79*I80 -> 110000 | J81: =J79*J80 -> 115000 | K81: Derived | L81: Low | M81: Email subs × $5 heuristic | N81: Simple database value proxy.
A82: 76 | B82: Digital / Brand | C82: Social audience (aggregate est.) | D82: followers | E82: =Assumptions!C49 -> 150000 | F82: =Assumptions!D49 -> 165000 | G82: =Assumptions!E49 -> 180000 | H82: =Assumptions!F49 -> 195000 | I82: =Assumptions!G49 -> 205000 | J82: =Assumptions!H49 -> 215000 | K82: Estimate | L82: Low | M82: Public social snippets | N82: Approximate total audience across major platforms.
A83: 77 | B83: Digital / Brand | C83: Website monthly visits | D83: visits | E83: =Assumptions!C50 -> 28000 | F83: =Assumptions!D50 -> 29000 | G83: =Assumptions!E50 -> 31000 | H83: =Assumptions!F50 -> 33000 | I83: =Assumptions!G50 -> 35200 | J83: =Assumptions!H50 -> 38016 | K83: Estimate / projection | L83: Medium | M83: Similarweb | N83: Current-year anchor plus historical trend/projection.
A84: 78 | B84: Digital / Brand | C84: Bounce rate | D84: pct | E84: =Assumptions!C51 -> 0.5 | F84: =Assumptions!D51 -> 0.495 | G84: =Assumptions!E51 -> 0.49 | H84: =Assumptions!F51 -> 0.48 | I84: =Assumptions!G51 -> 0.4725 | J84: =Assumptions!H51 -> 0.465 | K84: Estimate / projection | L84: Medium | M84: Similarweb | N84: Current-year anchor plus trend.
A85: 79 | B85: Digital / Brand | C85: Pages per visit | D85: pages | E85: =Assumptions!C52 -> 1.55 | F85: =Assumptions!D52 -> 1.6 | G85: =Assumptions!E52 -> 1.65 | H85: =Assumptions!F52 -> 1.72 | I85: =Assumptions!G52 -> 1.8 | J85: =Assumptions!H52 -> 1.9 | K85: Estimate / projection | L85: Medium | M85: Similarweb | N85: Current-year anchor plus trend.
A86: 80 | B86: Digital / Brand | C86: Average visit duration (sec) | D86: sec | E86: =Assumptions!C53 -> 60 | F86: =Assumptions!D53 -> 62 | G86: =Assumptions!E53 -> 65 | H86: =Assumptions!F53 -> 68 | I86: =Assumptions!G53 -> 70 | J86: =Assumptions!H53 -> 75 | K86: Estimate / projection | L86: Medium | M86: Similarweb | N86: Current-year anchor plus trend.
A87: 81 | B87: Digital / Brand | C87: Organic search share | D87: pct | E87: =Assumptions!C54 -> 0.4 | F87: =Assumptions!D54 -> 0.41 | G87: =Assumptions!E54 -> 0.43 | H87: =Assumptions!F54 -> 0.44 | I87: =Assumptions!G54 -> 0.4551 | J87: =Assumptions!H54 -> 0.46 | K87: Estimate / projection | L87: Medium | M87: Similarweb | N87: Current-year anchor plus trend.
A88: 82 | B88: Digital / Brand | C88: Customer acquisition cost | D88: $ | E88: =Assumptions!C55 -> 45 | F88: =Assumptions!D55 -> 44 | G88: =Assumptions!E55 -> 42 | H88: =Assumptions!F55 -> 40 | I88: =Assumptions!G55 -> 39 | J88: =Assumptions!H55 -> 37 | K88: Estimate | L88: Low | M88: Model methodology | N88: Per-new-buyer marketing cost estimate.
A89: 83 | B89: Digital / Brand | C89: Net promoter score | D89: pts | E89: =Assumptions!C56 -> 45 | F89: =Assumptions!D56 -> 43 | G89: =Assumptions!E56 -> 46 | H89: =Assumptions!F56 -> 50 | I89: =Assumptions!G56 -> 54 | J89: =Assumptions!H56 -> 56 | K89: Estimate | L89: Low | M89: Model methodology | N89: Sentiment proxy, not official survey.
A90: 84 | B90: Digital / Brand | C90: Foundation asset base | D90: $ | E90: =Assumptions!C81 -> 200000 | F90: =Assumptions!D81 -> 220000 | G90: =Assumptions!E81 -> 240000 | H90: =Assumptions!F81 -> 260000 | I90: =Assumptions!G81 -> 280000 | J90: =Assumptions!H81 -> 300000 | K90: Estimate | L90: Low | M90: Official foundation giving + model | N90: Logical asset placeholder.
A91: 85 | B91: Digital / Brand | C91: Affiliate synergy value | D91: $ | E91: =Assumptions!C82 -> 650000 | F91: =Assumptions!D82 -> 700000 | G91: =Assumptions!E82 -> 750000 | H91: =Assumptions!F82 -> 800000 | I91: =Assumptions!G82 -> 900000 | J91: =Assumptions!H82 -> 950000 | K91: Estimate | L91: Low | M91: Model methodology | N91: Ducks ecosystem cross-promotional value.
A92: 86 | B92: Digital / Brand | C92: Trademark / brand asset value | D92: $ | E92: =Assumptions!C83 -> 300000 | F92: =Assumptions!D83 -> 325000 | G92: =Assumptions!E83 -> 350000 | H92: =Assumptions!F83 -> 375000 | I92: =Assumptions!G83 -> 425000 | J92: =Assumptions!H83 -> 450000 | K92: Estimate | L92: Low | M92: Model methodology | N92: Logical brand asset placeholder.
A93: 6. Profitability, Efficiency & Valuation
A94: 87 | B94: Valuation | C94: EBITDA margin | D94: pct | E94: =IFERROR(E95/E49,"") -> 0.1063207 | F94: =IFERROR(F95/F49,"") -> 0.1242358 | G94: =IFERROR(G95/G49,"") -> 0.075043508 | H94: =IFERROR(H95/H49,"") -> 0.090665204 | I94: =IFERROR(I95/I49,"") -> 0.11115092 | J94: =IFERROR(J95/J49,"") -> 0.13982113 | K94: Derived | L94: Medium | M94: Modeled margin from cost stack | N94: Calculated from EBITDA ÷ gross revenue.
A95: 88 | B95: Valuation | C95: EBITDA | D95: $ | E95: =E49-E96 -> 899263.74 | F95: =F49-F96 -> 1112461.9 | G95: =G49-G96 -> 733312.52 | H95: =H49-H96 -> 943447.46 | I95: =I49-I96 -> 1246049.4 | J95: =J49-J96 -> 1682309 | K95: Derived | L95: Medium | M95: Gross revenue less modeled operating cost stack | N95: Operating earnings proxy excluding parent subsidy.
A96: 89 | B96: Valuation | C96: Operating expenses (modeled) | D96: $ | E96: =ROUND(E55+E58+E59+E60+E68+(E69*90000)+E70+E72+E75+E76+E64+(E49*0.22),0) -> 7558767 | F96: =ROUND(F55+F58+F59+F60+F68+(F69*90000)+F70+F72+F75+F76+F64+(F49*0.22),0) -> 7841977 | G96: =ROUND(G55+G58+G59+G60+G68+(G69*90000)+G70+G72+G75+G76+G64+(G49*0.22),0) -> 9038519 | H96: =ROUND(H55+H58+H59+H60+H68+(H69*90000)+H70+H72+H75+H76+H64+(H49*0.22),0) -> 9462391 | I96: =ROUND(I55+I58+I59+I60+I68+(I69*90000)+I70+I72+I75+I76+I64+(I49*0.22),0) -> 9964378 | J96: =ROUND(J55+J58+J59+J60+J68+(J69*90000)+J70+J72+J75+J76+J64+(J49*0.22),0) -> 10349556 | K96: Derived | L96: Medium | M96: Modeled cost stack | N96: Includes base rent, security, utilities, load-in, coaching, FO, medical, travel/housing proxy, insurance, equipment, tax, and other overhead.
A97: 90 | B97: Valuation | C97: Operating expense ratio | D97: pct | E97: =IFERROR(E96/E49,"") -> 0.8936793 | F97: =IFERROR(F96/F49,"") -> 0.8757642 | G97: =IFERROR(G96/G49,"") -> 0.92495649 | H97: =IFERROR(H96/H49,"") -> 0.9093348 | I97: =IFERROR(I96/I49,"") -> 0.88884908 | J97: =IFERROR(J96/J49,"") -> 0.86017887 | K97: Derived | L97: Medium | M97: OpEx ÷ gross revenue | N97: Team-level modeled expense ratio.
A98: 91 | B98: Valuation | C98: Revenue multiple | D98: x | E98: =Assumptions!C84 -> 3.2 | F98: =Assumptions!D84 -> 3.2 | G98: =Assumptions!E84 -> 3.2 | H98: =Assumptions!F84 -> 3.2 | I98: =Assumptions!G84 -> 3.2 | J98: =Assumptions!H84 -> 3.2 | K98: Control | L98: Medium | M98: User assumption | N98: Valuation multiple.
A99: 92 | B99: Valuation | C99: Implied franchise valuation | D99: $ | E99: =E49*E98 -> 27065698 | F99: =F49*F98 -> 28654205 | G99: =G49*G98 -> 31269861 | H99: =H49*H98 -> 33298683 | I99: =I49*I98 -> 35873368 | J99: =J49*J98 -> 38501968 | K99: Derived | L99: Medium | M99: Gross revenue × 3.2x multiple | N99: User-specified multiple applied to gross revenue.

Sheet Scenario_OnePager
A1: 2026-27 Projection Upside — Revenue, EBITDA & Value Creation Levers
A2: Baseline uses the Master_Model. Scenario columns show how disciplined operations, pricing, sponsorship and digital execution can move the club to a higher operating ceiling.
A4: Baseline Revenue | D4: Baseline EBITDA | G4: Baseline Valuation | J4: Baseline Attendance
A5: =Master_Model!J49 -> 12031865 | D5: =Master_Model!J95 -> 1682309 | G5: =Master_Model!J99 -> 38501968 | J5: =Master_Model!J3 -> 7625
A8: Lever / Output | B8: Efficiency / Ops | C8: Sales & Retention | D8: Premium + Sponsorship | F8: Recommended Actions to Push the Curve Higher
A9: Attendance uplift | B9: 0.02 | C9: 0.04 | D9: 0.06 | F9: 1) OPERATIONS / CRM CLEAN-UP • Remove stale ticket copy and unify current-season pricing across pages. • Standardize lead-source tagging and post-game follow-up windows. • Weekly dashboard: STM churn, second-game conversion, group close rate, per-cap spend.
A10: WATP uplift | B10: 0.015 | C10: 0.025 | D10: 0.04
A11: Per-cap uplift | B11: 0.03 | C11: 0.05 | D11: 0.07
A12: Sponsorship uplift | B12: 0.04 | C12: 0.08 | D12: 0.12
A13: EBITDA margin uplift | B13: 0.003 | C13: 0.006 | D13: 0.01 | F13: 2) SALES & RETENTION ENGINE • Build first-game-to-second-game journeys for single-game, student and family-pack buyers. • Expand military, youth sports and corporate group calendars around promo nights. • Tighten STM save offers 60–90 days before renewal deadlines.
A16: Lever / Output | B16: Efficiency / Ops | C16: Sales & Retention | D16: Premium + Sponsorship
A17: Projected attendance | B17: =ROUND(Master_Model!J3*(1+B9),0) -> 7778 | C17: =ROUND(Master_Model!J3*(1+C9),0) -> 7930 | D17: =ROUND(Master_Model!J3*(1+D9),0) -> 8083 | F17: 3) PREMIUM / SPONSORSHIP / DIGITAL • Package Stella Lounge, suites and premium parking into higher-yield bundles. • Sell more digital presented-by inventory across app, email and social. • Expand bar-network and watch-party capture into lead generation, not just branding.
A18: Projected WATP | B18: =Master_Model!J22*(1+B10) -> 26.60315 | C18: =Master_Model!J22*(1+C10) -> 26.86525 | D18: =Master_Model!J22*(1+D10) -> 27.2584
A19: Projected per-cap | B19: =Master_Model!J41*(1+B11) -> 21.321 | C19: =Master_Model!J41*(1+C11) -> 21.735 | D19: =Master_Model!J41*(1+D11) -> 22.149
A20: Projected sponsorship | B20: =Master_Model!J42*(1+B12) -> 3069144 | C20: =Master_Model!J42*(1+C12) -> 3187188 | D20: =Master_Model!J42*(1+D12) -> 3305232
A21: Incremental gate revenue | B21: =(B17*Master_Model!J4*B18)-Master_Model!J28 -> 254449.83 | C21: =(C17*Master_Model!J4*C18)-Master_Model!J28 -> 474846.57 | D21: =(D17*Master_Model!J4*D18)-Master_Model!J28 -> 737222.3
A22: Incremental ancillary revenue | B22: =(B17*Master_Model!J4*B19)-(Master_Model!J5*Master_Model!J41) -> 287900.57 | C22: =(C17*Master_Model!J4*C19)-(Master_Model!J5*Master_Model!J41) -> 522757.8 | D22: =(D17*Master_Model!J4*D19)-(Master_Model!J5*Master_Model!J41) -> 762943.21
A23: Incremental sponsorship | B23: =B20-Master_Model!J42 -> 118044 | C23: =C20-Master_Model!J42 -> 236088 | D23: =D20-Master_Model!J42 -> 354132
A24: Total incremental revenue | B24: =SUM(B21:B23) -> 660394.39 | C24: =SUM(C21:C23) -> 1233692.4 | D24: =SUM(D21:D23) -> 1854297.5
A25: Projected total revenue | B25: =Master_Model!J49+B24 -> 12692259 | C25: =Master_Model!J49+C24 -> 13265557 | D25: =Master_Model!J49+D24 -> 13886163
A26: Projected EBITDA | B26: =B25*(Master_Model!J94+B13) -> 1812722.9 | C26: =C25*(Master_Model!J94+C13) -> 1934398.6 | D26: =D25*(Master_Model!J94+D13) -> 2080440.6
A27: Projected valuation | B27: =B25*Master_Model!J98 -> 40615230 | C27: =C25*Master_Model!J98 -> 42449784 | D27: =D25*Master_Model!J98 -> 44435720

Sheet Source_Log
A1: Column1 | B1: Category | C1: 2021-22 | D1: 2022-23 | E1: 2023-24 | F1: 2024-25 | G1: 2025-26 | H1: 2026-27 | I1: Unit | J1: Source / Method | K1: Status
A2: 2026-27 attendance growth assumption | B2: CONTROL | H2: 0.03 | I2: pct | J2: Model control | K2: Control
A3: 2026-27 WATP growth assumption | B3: CONTROL | H3: 0.032 | I3: pct | J3: Model control | K3: Control
A4: 2026-27 sponsorship growth assumption | B4: CONTROL | H4: 0.093 | I4: pct | J4: Model control | K4: Control
A5: 2026-27 per-cap F&B growth assumption | B5: CONTROL | H5: 0.032 | I5: pct | J5: Model control | K5: Control
A6: 2026-27 merch per-cap growth assumption | B6: CONTROL | H6: 0.044 | I6: pct | J6: Model control | K6: Control
A7: 2026-27 STM price growth assumption | B7: CONTROL | H7: 0.03 | I7: pct | J7: Model control | K7: Control
A8: 2026-27 single-game price growth assumption | B8: CONTROL | H8: 0.043 | I8: pct | J8: Model control | K8: Control
A9: 2026-27 website traffic growth assumption | B9: CONTROL | H9: 0.08 | I9: pct | J9: Model control | K9: Control
A10: Average attendance | B10: ATTENDANCE | C10: 6992 | D10: 6953 | E10: 7249 | F10: 7262 | G10: 7403 | I10: fans/game | J10: https://www.hockeydb.com/stte/san-diego-gulls-11619.html | K10: Public/Projection
A11: Home games | B11: ATTENDANCE | C11: 34 | D11: 36 | E11: 36 | F11: 36 | G11: 36 | H11: 36 | I11: games | J11: https://www.sandiegogulls.com/news/detail/san-diego-gulls-2021-22-schedule-announced | K11: Public
A12: Hockey seating capacity | B12: VENUE | C12: 12920 | D12: 12920 | E12: 12920 | F12: 12920 | G12: 12920 | H12: 12920 | I12: seats | J12: https://www.sandiegogulls.com/assets/doc/2021-22-San-Diego-Gulls-Media-Guide-compressed-92470e4558.pdf | K12: Context
A13: General venue capacity | B13: VENUE | C13: 14000 | D13: 14000 | E13: 14000 | F13: 14000 | G13: 14000 | H13: 14000 | I13: seats | J13: https://pechangaarenasd.com/about/ | K13: Public
A14: Home weekend dates | B14: SCHEDULE | C14: 23 | D14: 23 | E14: 26 | F14: 25 | G14: 25 | H14: 25 | I14: dates | J14: Multiple official schedule releases on sandiegogulls.com | K14: Public
A15: Friday home games | B15: SCHEDULE | C15: 11 | D15: 12 | E15: 12 | F15: 9 | G15: 10 | H15: 10 | I15: games | J15: Multiple official schedule releases on sandiegogulls.com | K15: Public
A16: Saturday home games | B16: SCHEDULE | C16: 11 | D16: 11 | E16: 12 | F16: 14 | G16: 10 | H16: 11 | I16: games | J16: Multiple official schedule releases on sandiegogulls.com | K16: Public/Projection
A17: Sunday home games | B17: SCHEDULE | C17: 1 | D17: 1 | E17: 2 | F17: 2 | G17: 5 | H17: 4 | I17: games | J17: Multiple official schedule releases on sandiegogulls.com | K17: Public/Projection
A18: Back-to-back sets | B18: SCHEDULE | C18: 24 | D18: 21 | E18: 18 | F18: 20 | G18: 22 | H18: 22 | I18: sets | J18: Multiple official schedule releases on sandiegogulls.com | K18: Public
A19: Promotional/theme nights announced | B19: MARKETING | C19: 13 | D19: 15 | E19: 16 | F19: 23 | G19: 28 | H19: 30 | I19: nights | J19: Multiple official promo releases on sandiegogulls.com | K19: Public/Projection
A20: Giveaway items announced | B20: MARKETING | C20: 7 | D20: 6 | E20: 10 | F20: 11 | G20: 5 | H20: 6 | I20: items | J20: Multiple official promo releases on sandiegogulls.com | K20: Public/Projection
A21: Pregame tailgates | B21: MARKETING | C21: 6 | D21: 6 | E21: 7 | F21: 7 | G21: 7 | H21: 8 | I21: events | J21: Multiple official promo releases on sandiegogulls.com | K21: Public/Projection
A22: STM entry price | B22: TICKETING | C22: 476 | D22: 540 | E22: 540 | F22: 560 | G22: 614 | I22: $/seat | J22: Multiple official ticketing releases on sandiegogulls.com | K22: Public/Projection
A23: Single-game floor (box office / public) | B23: TICKETING | C23: 19 | D23: 21 | E23: 20 | F23: 22 | G23: 23 | I23: $/ticket | J23: Multiple official ticketing releases on sandiegogulls.com | K23: Public/Estimate/Projection
A24: Single-game floor (online incl. fees) | B24: TICKETING | F24: 27.5 | G24: 28.75 | H24: 29.75 | I24: $/ticket | J24: https://www.sandiegogulls.com/news/detail/single-game-tickets-available-now | K24: Estimate/Projection
A25: College ticket price | B25: TICKETING | G25: 17 | H25: 17.5 | I25: $/ticket | J25: https://www.sandiegogulls.com/tickets/college | K25: Public/Projection
A26: Family pack price floor | B26: TICKETING | G26: 130 | H26: 135 | I26: $/pack | J26: https://www.sandiegogulls.com/tickets/4-packs | K26: Public/Projection
A27: Group minimum size | B27: TICKETING | C27: 10 | D27: 10 | E27: 10 | F27: 10 | G27: 10 | H27: 10 | I27: tickets | J27: https://www.sandiegogulls.com/tickets/group-tickets | K27: Public/Context
A28: Max mini-plan discount | B28: TICKETING | C28: 0.15 | D28: 0.15 | E28: 0.2 | F28: 0.3 | G28: 0.3 | H28: 0.3 | I28: pct | J28: https://www.sandiegogulls.com/tickets/gulls-mini-plans | K28: Estimate/Projection
A29: Weighted average ticket price (modeled) | B29: TICKETING | C29: 22 | D29: 22.4 | E29: 23.4 | F29: 24.4 | G29: 25.4 | I29: $/ticket | J29: Model methodology | K29: Estimate/Projection
A30: Group sales share of gate | B30: TICKETING | C30: 0.16 | D30: 0.17 | E30: 0.18 | F30: 0.19 | G30: 0.2 | H30: 0.21 | I30: pct | J30: Model methodology | K30: Estimate/Projection
A31: Premium seating yield (included in gate) | B31: TICKETING | C31: 380000 | D31: 400000 | E31: 460000 | F31: 520000 | G31: 600000 | H31: 660000 | I31: $ | J31: Model methodology | K31: Estimate/Projection
A32: STM base (full-season equivalents) | B32: TICKETING | C32: 2300 | D32: 2350 | E32: 2450 | F32: 2550 | G32: 2700 | H32: 2780 | I32: FSE | J32: Model methodology | K32: Estimate/Projection
A33: STM retention rate | B33: TICKETING | C33: 0.77 | D33: 0.76 | E33: 0.78 | F33: 0.8 | G33: 0.82 | H33: 0.83 | I33: pct | J33: Model methodology | K33: Estimate/Projection
A34: F&B per-cap gross | B34: ANCILLARY | C34: 13 | D34: 13.4 | E34: 14 | F34: 14.8 | G34: 15.5 | I34: $/attendee | J34: Model methodology | K34: Estimate/Projection
A35: Team concession commission rate | B35: ANCILLARY | C35: 0.04 | D35: 0.04 | E35: 0.04 | F35: 0.04 | G35: 0.04 | H35: 0.04 | I35: pct | J35: Model methodology | K35: Estimate
A36: Merchandise per-cap | B36: ANCILLARY | C36: 3.6 | D36: 3.8 | E36: 4 | F36: 4.2 | G36: 4.5 | I36: $/attendee | J36: Model methodology | K36: Estimate/Projection
A37: Parking fee assumption | B37: ANCILLARY | C37: 15 | D37: 15 | E37: 15 | F37: 18 | G37: 20 | H37: 21 | I37: $/vehicle | J37: https://pechangaarenasd.com/plan-your-visit/directions-parking/ | K37: Estimate/Projection
A38: Average auto occupancy | B38: ANCILLARY | C38: 2.6 | D38: 2.6 | E38: 2.6 | F38: 2.5 | G38: 2.5 | H38: 2.5 | I38: persons/vehicle | J38: Model methodology | K38: Estimate
A39: Team share of parking | B39: ANCILLARY | C39: 0.05 | D39: 0.05 | E39: 0.05 | F39: 0.05 | G39: 0.05 | H39: 0.05 | I39: pct | J39: Model methodology | K39: Estimate
A40: Total sponsorship revenue | B40: SPONSORSHIP | C40: 1950000 | D40: 2000000 | E40: 2200000 | F40: 2450000 | G40: 2700000 | I40: $ | J40: Model methodology | K40: Estimate/Projection
A41: Title partner value | B41: SPONSORSHIP | C41: 450000 | D41: 450000 | E41: 480000 | F41: 500000 | G41: 550000 | H41: 580000 | I41: $ | J41: Model methodology | K41: Estimate
A42: Jersey / patch revenue | B42: SPONSORSHIP | C42: 0 | D42: 0 | E42: 150000 | F42: 180000 | G42: 200000 | H42: 220000 | I42: $ | J42: Model methodology | K42: Estimate
A43: Digital inventory yield | B43: SPONSORSHIP | C43: 80000 | D43: 90000 | E43: 110000 | F43: 130000 | G43: 150000 | H43: 165000 | I43: $ | J43: Model methodology | K43: Estimate
A44: Broadcast / streaming value | B44: MEDIA | C44: 150000 | D44: 100000 | E44: 100000 | F44: 110000 | G44: 130000 | H44: 145000 | I44: $ | J44: https://theahl.com/news/ahl-flosports-partnership-extension | K44: Estimate
A45: Email subscribers (estimated active) | B45: DIGITAL | C45: 18000 | D45: 19000 | E45: 20000 | F45: 21000 | G45: 22000 | H45: 23000 | I45: subs | J45: Model methodology | K45: Estimate
A46: Social audience (aggregate est.) | B46: DIGITAL | C46: 150000 | D46: 165000 | E46: 180000 | F46: 195000 | G46: 205000 | H46: 215000 | I46: followers | J46: Multiple public social snippets | K46: Estimate
A47: Website monthly visits | B47: DIGITAL | C47: 28000 | D47: 29000 | E47: 31000 | F47: 33000 | G47: 35200 | I47: visits | J47: https://www.similarweb.com/website/sandiegogulls.com/ | K47: Estimate/Projection
A48: Bounce rate | B48: DIGITAL | C48: 0.5 | D48: 0.495 | E48: 0.49 | F48: 0.48 | G48: 0.4725 | H48: 0.465 | I48: pct | J48: https://www.similarweb.com/website/sandiegogulls.com/ | K48: Estimate/Projection
A49: Pages per visit | B49: DIGITAL | C49: 1.55 | D49: 1.6 | E49: 1.65 | F49: 1.72 | G49: 1.8 | H49: 1.9 | I49: pages | J49: https://www.similarweb.com/website/sandiegogulls.com/ | K49: Estimate/Projection
A50: Average visit duration (sec) | B50: DIGITAL | C50: 60 | D50: 62 | E50: 65 | F50: 68 | G50: 70 | H50: 75 | I50: sec | J50: https://www.similarweb.com/website/sandiegogulls.com/ | K50: Estimate/Projection
A51: Organic search share | B51: DIGITAL | C51: 0.4 | D51: 0.41 | E51: 0.43 | F51: 0.44 | G51: 0.4551 | H51: 0.46 | I51: pct | J51: https://www.similarweb.com/website/sandiegogulls.com/ | K51: Estimate/Projection
A52: Customer acquisition cost | B52: MARKETING | C52: 45 | D52: 44 | E52: 42 | F52: 40 | G52: 39 | H52: 37 | I52: $/new buyer | J52: Model methodology | K52: Estimate
A53: Net promoter score | B53: MARKETING | C53: 45 | D53: 43 | E53: 46 | F53: 50 | G53: 54 | H53: 56 | I53: pts | J53: Model methodology | K53: Estimate
A54: Facility fee per paid ticket | B54: ARENA | E54: 2.5 | F54: 3 | G54: 3 | H54: 3 | I54: $/ticket | J54: Lease-era reporting / model assumption | K54: Estimate
A55: Base rent floor (annualized) | B55: ARENA | E55: 775716 | F55: 799107 | G55: 823084 | H55: 839546 | I55: $ | J55: https://www.lee-associates.com/elee/utc/newsletter/091224/article3.pdf | K55: Public/Projection
A56: Rent escalator | B56: ARENA | F56: 0.03 | G56: 0.03 | H56: 0.02 | I56: pct | J56: Lease-era reporting / model assumption | K56: Derived/Projection
A57: Security / police overhead per event | B57: ARENA | C57: 12000 | D57: 12000 | E57: 13000 | F57: 14000 | G57: 15000 | H57: 15500 | I57: $ | J57: https://www.sandiego.gov/sites/default/files/specialeventsopsmanual2020.pdf | K57: Estimate
A58: Utilities & HVAC load | B58: ARENA | C58: 180000 | D58: 190000 | E58: 210000 | F58: 230000 | G58: 250000 | H58: 260000 | I58: $ | J58: Model methodology | K58: Estimate
A59: Load-in / load-out allocation | B59: ARENA | C59: 80000 | D59: 85000 | E59: 90000 | F59: 95000 | G59: 100000 | H59: 105000 | I59: $ | J59: Model methodology | K59: Estimate
A60: Midway district assessment / CFD | B60: ARENA | C60: 0 | D60: 0 | E60: 0 | F60: 0 | G60: 0 | H60: 0 | I60: $ | J60: Public review | K60: Context
A61: Lease horizon (months remaining) | B61: ARENA | E61: 29 | F61: 17 | G61: 5 | H61: 0 | I61: months | J61: https://www.sandiego.gov/economic-development/real-estate/midway-rising | K61: Estimate
A62: Naming-rights tranche allocable to team ops | B62: ARENA | C62: 250000 | D62: 250000 | E62: 260000 | F62: 275000 | G62: 300000 | H62: 310000 | I62: $ | J62: Model methodology | K62: Estimate
A63: Tax liability | B63: ARENA | C63: 50000 | D63: 50000 | E63: 50000 | F63: 50000 | G63: 50000 | H63: 50000 | I63: $ | J63: Model methodology | K63: Estimate
A64: Debt-to-value ratio | B64: ARENA | C64: 0.05 | D64: 0.05 | E64: 0.05 | F64: 0.05 | G64: 0.05 | H64: 0.05 | I64: pct | J64: Model methodology | K64: Estimate
A65: Roster headcount | B65: HUMAN CAPITAL | C65: 22 | D65: 24 | E65: 26 | F65: 22 | G65: 29 | H65: 29 | I65: players | J65: Multiple official roster/game notes sources | K65: Public/Projection
A66: Coaching staff payroll | B66: HUMAN CAPITAL | C66: 550000 | D66: 560000 | E66: 580000 | F66: 620000 | G66: 680000 | H66: 710000 | I66: $ | J66: Model methodology | K66: Estimate
A67: Front office FTE | B67: HUMAN CAPITAL | C67: 42 | D67: 43 | E67: 44 | F67: 45 | G67: 46 | H67: 47 | I67: FTE | J67: https://www.linkedin.com/company/san-diego-gulls | K67: Estimate
A68: Medical / training tech spend | B68: HUMAN CAPITAL | C68: 100000 | D68: 110000 | E68: 130000 | F68: 150000 | G68: 175000 | H68: 185000 | I68: $ | J68: Model methodology | K68: Estimate
A69: Travel logistics ratio (air-heavy) | B69: HUMAN CAPITAL | C69: 0.82 | D69: 0.82 | E69: 0.83 | F69: 0.84 | G69: 0.84 | H69: 0.84 | I69: pct | J69: Model methodology | K69: Estimate
A70: Player housing spend | B70: HUMAN CAPITAL | C70: 200000 | D70: 210000 | E70: 230000 | F70: 250000 | G70: 280000 | H70: 290000 | I70: $ | J70: Model methodology | K70: Estimate
A71: AHL-only salary floor | B71: HUMAN CAPITAL | C71: 49000 | D71: 50000 | E71: 51500 | F71: 52725 | G71: 54000 | H71: 55620 | I71: $ | J71: https://phpa.com/site/agreements | K71: Estimate/Projection
A72: AHL-only average salary | B72: HUMAN CAPITAL | C72: 65000 | D72: 66000 | E72: 70000 | F72: 74000 | G72: 78000 | H72: 80000 | I72: $ | J72: Model methodology | K72: Estimate
A73: Insurance premiums | B73: HUMAN CAPITAL | C73: 200000 | D73: 210000 | E73: 230000 | F73: 250000 | G73: 270000 | H73: 280000 | I73: $ | J73: Model methodology | K73: Estimate
... A82: Email database value per active subscriber | B82: DIGITAL | C82: 5 | D82: 5 | E82: 5 | F82: 5 | G82: 5 | H82: 5 | I82: $/active sub | J82: Model control | K82: Control

Sheet Charts
A1: Column1 | B1: 2021-22 | C1: 2022-23 | D1: 2023-24 | E1: 2024-25 | F1: 2025-26 | G1: 2026-27
A2: Average Attendance | B2: =Master_Model!E3 -> 6992 | C2: =Master_Model!F3 -> 6953 | D2: =Master_Model!G3 -> 7249 | E2: =Master_Model!H3 -> 7262 | F2: =Master_Model!I3 -> 7403 | G2: =Master_Model!J3 -> 7625
A3: Gross Revenue | B3: =Master_Model!E49 -> 8458030.7 | C3: =Master_Model!F49 -> 8954438.9 | D3: =Master_Model!G49 -> 9771831.5 | E3: =Master_Model!H49 -> 10405838 | F3: =Master_Model!I49 -> 11210427 | G3: =Master_Model!J49 -> 12031865
A4: EBITDA | B4: =Master_Model!E95 -> 899263.74 | C4: =Master_Model!F95 -> 1112461.9 | D4: =Master_Model!G95 -> 733312.52 | E4: =Master_Model!H95 -> 943447.46 | F4: =Master_Model!I95 -> 1246049.4 | G4: =Master_Model!J95 -> 1682309
A5: Implied Valuation | B5: =Master_Model!E99 -> 27065698 | C5: =Master_Model!F99 -> 28654205 | D5: =Master_Model!G99 -> 31269861 | E5: =Master_Model!H99 -> 33298683 | F5: =Master_Model!I99 -> 35873368 | G5: =Master_Model!J99 -> 38501968
A8: Scenario | B8: Baseline | C8: Efficiency / Ops | D8: Sales & Retention | E8: Premium + Sponsorship
A9: Revenue | B9: =Master_Model!J49 -> 12031865 | C9: =Scenario_OnePager!B25 -> 12692259 | D9: =Scenario_OnePager!C25 -> 13265557 | E9: =Scenario_OnePager!D25 -> 13886163
A10: EBITDA | B10: =Master_Model!J95 -> 1682309 | C10: =Scenario_OnePager!B26 -> 1812722.9 | D10: =Scenario_OnePager!C26 -> 1934398.6 | E10: =Scenario_OnePager!D26 -> 2080440.6
