Workbook
Name Dashboard_Scenario_Input: 'Executive_Dashboard'!$C$3
Name Scenario_Selector: 'Assumptions'!$B$5
Name Attendance_Growth_Rate: 'Assumptions'!$B$6
Name WATP_Growth_Rate: 'Assumptions'!$B$7
Name Sponsorship_Growth_Rate: 'Assumptions'!$B$8
Name FB_Growth_Rate: 'Assumptions'!$B$9
Name Merch_Growth_Rate: 'Assumptions'!$B$10
Name STM_Growth_Rate: 'Assumptions'!$B$11
Name Single_Game_Growth_Rate: 'Assumptions'!$B$12
Name Website_Growth_Rate: 'Assumptions'!$B$13

Sheet Executive_Dashboard
B1: SAN DIEGO GULLS — EXECUTIVE DASHBOARD
B2: 2021-22 to 2026-27 forensic operating model | public anchors + interactive scenario planning
B3: Scenario | C3: Baseline | E3: Model status | F3: Live / scenario-linked
B5: Projected FY27 Revenue | E5: EBITDA Margin % | H5: Implied Franchise Value | K5: Attendance Capacity %
B6: =IFERROR(Master_Model!$J$52,0) | E6: =IFERROR(Master_Model!$J$97,0) | H6: =IFERROR(Master_Model!$J$102,0) | K6: =IFERROR(Master_Model!$J$6/Assumptions!$H$26,0)
B11: Open Scenario Levers | E11: Open Benchmarks | H11: Open Assumptions | K11: Open Source Log
B14: Executive readout • Attendance recovered from 6,992 (FY22) to 7,403 (FY26). • Private economics remain labeled as modeled estimates. • Changing the scenario switch updates FY27 revenue, EBITDA, valuation, and charts instantly. • Tactical upside comes from demand generation, ticket yield, sponsorship packaging, and digital conversion. | H14: What makes this decision-ready • Inputs and formulas are separated. • Scenario controls are validated and protected. • Master_Model is hidden for executive use but available for audit. • One-pager includes operational impact and competitor benchmarking. • Key assumption cells carry URL comments for auditability.
A23: Metric | B23: 2021-22 | C23: 2022-23 | D23: 2023-24 | E23: 2024-25 | F23: 2025-26 | G23: 2026-27
A24: Attendance | B24: =IFERROR(Master_Model!E6,0) | C24: =IFERROR(Master_Model!F6,0) | D24: =IFERROR(Master_Model!G6,0) | E24: =IFERROR(Master_Model!H6,0) | F24: =IFERROR(Master_Model!I6,0) | G24: =IFERROR(Master_Model!J6,0)
A25: Revenue | B25: =IFERROR(Master_Model!E52,0) | C25: =IFERROR(Master_Model!F52,0) | D25: =IFERROR(Master_Model!G52,0) | E25: =IFERROR(Master_Model!H52,0) | F25: =IFERROR(Master_Model!I52,0) | G25: =IFERROR(Master_Model!J52,0)
A26: EBITDA | B26: =IFERROR(Master_Model!E98,0) | C26: =IFERROR(Master_Model!F98,0) | D26: =IFERROR(Master_Model!G98,0) | E26: =IFERROR(Master_Model!H98,0) | F26: =IFERROR(Master_Model!I98,0) | G26: =IFERROR(Master_Model!J98,0)
A27: Valuation | B27: =IFERROR(Master_Model!E102,0) | C27: =IFERROR(Master_Model!F102,0) | D27: =IFERROR(Master_Model!G102,0) | E27: =IFERROR(Master_Model!H102,0) | F27: =IFERROR(Master_Model!I102,0) | G27: =IFERROR(Master_Model!J102,0)

Sheet Assumptions
A1: San Diego Gulls — Assumptions, Controls & Public Inputs
A2: Executive control lives on the dashboard. Yellow cells are editable scenario rates. The 2026-27 column is formula-driven and scenario-sensitive.
A4: Scenario Control | F4: Scenario Rate Matrix
A5: Scenario Selector (mirrors dashboard) | B5: =Executive_Dashboard!$C$3 | F5: Driver | G5: Baseline | H5: Tactical Upside | I5: Aggressive Growth | J5: Strategic Use
A6: Attendance growth | B6: =IF(Scenario_Selector="Baseline",$G6,IF(Scenario_Selector="Tactical Upside",$H6,$I6)) | F6: Attendance growth | G6: 0.03 | H6: 0.06 | I6: 0.09 | J6: Demand generation
A7: WATP growth | B7: =IF(Scenario_Selector="Baseline",$G7,IF(Scenario_Selector="Tactical Upside",$H7,$I7)) | F7: WATP growth | G7: 0.032 | H7: 0.05 | I7: 0.075 | J7: Ticket yield
A8: Sponsorship growth | B8: =IF(Scenario_Selector="Baseline",$G8,IF(Scenario_Selector="Tactical Upside",$H8,$I8)) | F8: Sponsorship growth | G8: 0.093 | H8: 0.12 | I8: 0.16 | J8: Sellable inventory
A9: F&B per-cap growth | B9: =IF(Scenario_Selector="Baseline",$G9,IF(Scenario_Selector="Tactical Upside",$H9,$I9)) | F9: F&B per-cap growth | G9: 0.032 | H9: 0.05 | I9: 0.07 | J9: Hospitality uplift
A10: Merch per-cap growth | B10: =IF(Scenario_Selector="Baseline",$G10,IF(Scenario_Selector="Tactical Upside",$H10,$I10)) | F10: Merch per-cap growth | G10: 0.044 | H10: 0.06 | I10: 0.08 | J10: Brand conversion
A11: STM entry growth | B11: =IF(Scenario_Selector="Baseline",$G11,IF(Scenario_Selector="Tactical Upside",$H11,$I11)) | F11: STM entry growth | G11: 0.03 | H11: 0.045 | I11: 0.06 | J11: Renewal ladder
A12: Single-game growth | B12: =IF(Scenario_Selector="Baseline",$G12,IF(Scenario_Selector="Tactical Upside",$H12,$I12)) | F12: Single-game growth | G12: 0.043 | H12: 0.06 | I12: 0.085 | J12: Dynamic pricing
A13: Website traffic growth | B13: =IF(Scenario_Selector="Baseline",$G13,IF(Scenario_Selector="Tactical Upside",$H13,$I13)) | F13: Website traffic growth | G13: 0.08 | H13: 0.12 | I13: 0.16 | J13: Digital funnel
A15: Category | B15: Driver | C15: 2021-22 | D15: 2022-23 | E15: 2023-24 | F15: 2024-25 | G15: 2025-26 | H15: 2026-27
A16: CONTROL | B16: 2026-27 attendance growth assumption | H16: 0.03
A17: CONTROL | B17: 2026-27 WATP growth assumption | H17: 0.032
A18: CONTROL | B18: 2026-27 sponsorship growth assumption | H18: 0.093
A19: CONTROL | B19: 2026-27 per-cap F&B growth assumption | H19: 0.032
A20: CONTROL | B20: 2026-27 merch per-cap growth assumption | H20: 0.044
A21: CONTROL | B21: 2026-27 STM price growth assumption | H21: 0.03
A22: CONTROL | B22: 2026-27 single-game price growth assumption | H22: 0.043
A23: CONTROL | B23: 2026-27 website traffic growth assumption | H23: 0.08
A24: ATTENDANCE | B24: Average attendance | C24: 6992 | D24: 6953 | E24: 7249 | F24: 7262 | G24: 7403 | H24: =ROUND(G24*(1+Attendance_Growth_Rate),0)
A25: ATTENDANCE | B25: Home games | C25: 34 | D25: 36 | E25: 36 | F25: 36 | G25: 36 | H25: 36
A26: VENUE | B26: Hockey seating capacity | C26: 12920 | D26: 12920 | E26: 12920 | F26: 12920 | G26: 12920 | H26: 12920
A27: VENUE | B27: General venue capacity | C27: 14000 | D27: 14000 | E27: 14000 | F27: 14000 | G27: 14000 | H27: 14000
A28: SCHEDULE | B28: Home weekend dates | C28: 23 | D28: 23 | E28: 26 | F28: 25 | G28: 25 | H28: 25
A29: SCHEDULE | B29: Friday home games | C29: 11 | D29: 12 | E29: 12 | F29: 9 | G29: 10 | H29: 10
A30: SCHEDULE | B30: Saturday home games | C30: 11 | D30: 11 | E30: 12 | F30: 14 | G30: 10 | H30: 11
A31: SCHEDULE | B31: Sunday home games | C31: 1 | D31: 1 | E31: 2 | F31: 2 | G31: 5 | H31: 4
A32: SCHEDULE | B32: Back-to-back sets | C32: 24 | D32: 21 | E32: 18 | F32: 20 | G32: 22 | H32: 22
A33: MARKETING | B33: Promotional/theme nights announced | C33: 13 | D33: 15 | E33: 16 | F33: 23 | G33: 28 | H33: 30
A34: MARKETING | B34: Giveaway items announced | C34: 7 | D34: 6 | E34: 10 | F34: 11 | G34: 5 | H34: 6
A35: MARKETING | B35: Pregame tailgates | C35: 6 | D35: 6 | E35: 7 | F35: 7 | G35: 7 | H35: 8
A36: TICKETING | B36: STM entry price | C36: 476 | D36: 540 | E36: 540 | F36: 560 | G36: 614 | H36: =ROUND(G36*(1+STM_Growth_Rate),0)
A37: TICKETING | B37: Single-game floor (box office / public) | C37: 19 | D37: 21 | E37: 20 | F37: 22 | G37: 23 | H37: =ROUND(G37*(1+Single_Game_Growth_Rate),0)
A38: TICKETING | B38: Single-game floor (online incl. fees) | F38: 27.5 | G38: 28.75 | H38: =ROUND(G38*(1+Single_Game_Growth_Rate),2)
A39: TICKETING | B39: College ticket price | G39: 17 | H39: =ROUND(G39*1.03,2)
A40: TICKETING | B40: Family pack price floor | G40: 130 | H40: =ROUND(G40*1.04,0)
A41: TICKETING | B41: Group minimum size | C41: 10 | D41: 10 | E41: 10 | F41: 10 | G41: 10 | H41: 10
A42: TICKETING | B42: Max mini-plan discount | C42: 0.15 | D42: 0.15 | E42: 0.2 | F42: 0.3 | G42: 0.3 | H42: 0.3
A43: TICKETING | B43: Weighted average ticket price (modeled) | C43: 22 | D43: 22.4 | E43: 23.4 | F43: 24.4 | G43: 25.4 | H43: =ROUND(G43*(1+WATP_Growth_Rate),2)
A44: TICKETING | B44: Group sales share of gate | C44: 0.16 | D44: 0.17 | E44: 0.18 | F44: 0.19 | G44: 0.2 | H44: 0.21
A45: TICKETING | B45: Premium seating yield (included in gate) | C45: 380000 | D45: 400000 | E45: 460000 | F45: 520000 | G45: 600000 | H45: =ROUND(G45*(1+MAX(WATP_Growth_Rate,0.10)),0)
A46: TICKETING | B46: STM base (full-season equivalents) | C46: 2300 | D46: 2350 | E46: 2450 | F46: 2550 | G46: 2700 | H46: =ROUND(G46*(1+MIN(Attendance_Growth_Rate,0.03)),0)
A47: TICKETING | B47: STM retention rate | C47: 0.77 | D47: 0.76 | E47: 0.78 | F47: 0.8 | G47: 0.82 | H47: 0.83
A48: ANCILLARY | B48: F&B per-cap gross | C48: 13 | D48: 13.4 | E48: 14 | F48: 14.8 | G48: 15.5 | H48: =ROUND(G48*(1+FB_Growth_Rate),2)
A49: ANCILLARY | B49: Team concession commission rate | C49: 0.04 | D49: 0.04 | E49: 0.04 | F49: 0.04 | G49: 0.04 | H49: 0.04
A50: ANCILLARY | B50: Merchandise per-cap | C50: 3.6 | D50: 3.8 | E50: 4 | F50: 4.2 | G50: 4.5 | H50: =ROUND(G50*(1+Merch_Growth_Rate),2)
A51: ANCILLARY | B51: Parking fee assumption | C51: 15 | D51: 15 | E51: 15 | F51: 18 | G51: 20 | H51: 21
A52: ANCILLARY | B52: Average auto occupancy | C52: 2.6 | D52: 2.6 | E52: 2.6 | F52: 2.5 | G52: 2.5 | H52: 2.5
A53: ANCILLARY | B53: Team share of parking | C53: 0.05 | D53: 0.05 | E53: 0.05 | F53: 0.05 | G53: 0.05 | H53: 0.05
A54: SPONSORSHIP | B54: Total sponsorship revenue | C54: 1950000 | D54: 2000000 | E54: 2200000 | F54: 2450000 | G54: 2700000 | H54: =ROUND(G54*(1+Sponsorship_Growth_Rate),0)
A55: SPONSORSHIP | B55: Title partner value | C55: 450000 | D55: 450000 | E55: 480000 | F55: 500000 | G55: 550000 | H55: 580000
A56: SPONSORSHIP | B56: Jersey / patch revenue | C56: 0 | D56: 0 | E56: 150000 | F56: 180000 | G56: 200000 | H56: 220000
A57: SPONSORSHIP | B57: Digital inventory yield | C57: 80000 | D57: 90000 | E57: 110000 | F57: 130000 | G57: 150000 | H57: 165000
A58: MEDIA | B58: Broadcast / streaming value | C58: 150000 | D58: 100000 | E58: 100000 | F58: 110000 | G58: 130000 | H58: 145000
A59: DIGITAL | B59: Email subscribers (estimated active) | C59: 18000 | D59: 19000 | E59: 20000 | F59: 21000 | G59: 22000 | H59: =ROUND(G59*(1+MIN(Website_Growth_Rate,0.10)),0)
A60: DIGITAL | B60: Social audience (aggregate est.) | C60: 150000 | D60: 165000 | E60: 180000 | F60: 195000 | G60: 205000 | H60: =ROUND(G60*1.05,0)
A61: DIGITAL | B61: Website monthly visits | C61: 28000 | D61: 29000 | E61: 31000 | F61: 33000 | G61: 35200 | H61: =ROUND(G61*(1+Website_Growth_Rate),0)
A62: DIGITAL | B62: Bounce rate | C62: 0.5 | D62: 0.495 | E62: 0.49 | F62: 0.48 | G62: 0.4725 | H62: 0.465
A63: DIGITAL | B63: Pages per visit | C63: 1.55 | D63: 1.6 | E63: 1.65 | F63: 1.72 | G63: 1.8 | H63: 1.9
A64: DIGITAL | B64: Average visit duration (sec) | C64: 60 | D64: 62 | E64: 65 | F64: 68 | G64: 70 | H64: 75
A65: DIGITAL | B65: Organic search share | C65: 0.4 | D65: 0.41 | E65: 0.43 | F65: 0.44 | G65: 0.4551 | H65: =MIN(G65+0.005,0.60)
A66: MARKETING | B66: Customer acquisition cost | C66: 45 | D66: 44 | E66: 42 | F66: 40 | G66: 39 | H66: =ROUND(MAX(G66*(1-0.05),35),0)
A67: MARKETING | B67: Net promoter score | C67: 45 | D67: 43 | E67: 46 | F67: 50 | G67: 54 | H67: =ROUND(G67+2,0)
A68: ARENA | B68: Facility fee per paid ticket | E68: 2.5 | F68: 3 | G68: 3 | H68: 3
A69: ARENA | B69: Base rent floor (annualized) | E69: 775716 | F69: 799107 | G69: 823084 | H69: 839546
A70: ARENA | B70: Rent escalator | F70: 0.03 | G70: 0.03 | H70: 0.02
A71: ARENA | B71: Security / police overhead per event | C71: 12000 | D71: 12000 | E71: 13000 | F71: 14000 | G71: 15000 | H71: 15500
A72: ARENA | B72: Utilities & HVAC load | C72: 180000 | D72: 190000 | E72: 210000 | F72: 230000 | G72: 250000 | H72: 260000
A73: ARENA | B73: Load-in / load-out allocation | C73: 80000 | D73: 85000 | E73: 90000 | F73: 95000 | G73: 100000 | H73: 105000
A74: ARENA | B74: Midway district assessment / CFD | C74: 0 | D74: 0 | E74: 0 | F74: 0 | G74: 0 | H74: 0
A75: ARENA | B75: Lease horizon (months remaining) | E75: 29 | F75: 17 | G75: 5 | H75: 0
A76: ARENA | B76: Naming-rights tranche allocable to team ops | C76: 250000 | D76: 250000 | E76: 260000 | F76: 275000 | G76: 300000 | H76: 310000
A77: ARENA | B77: Tax liability | C77: 50000 | D77: 50000 | E77: 50000 | F77: 50000 | G77: 50000 | H77: 50000
A78: ARENA | B78: Debt-to-value ratio | C78: 0.05 | D78: 0.05 | E78: 0.05 | F78: 0.05 | G78: 0.05 | H78: 0.05
A79: HUMAN CAPITAL | B79: Roster headcount | C79: 22 | D79: 24 | E79: 26 | F79: 22 | G79: 29 | H79: 29
A80: HUMAN CAPITAL | B80: Coaching staff payroll | C80: 550000 | D80: 560000 | E80: 580000 | F80: 620000 | G80: 680000 | H80: 710000
A81: HUMAN CAPITAL | B81: Front office FTE | C81: 42 | D81: 43 | E81: 44 | F81: 45 | G81: 46 | H81: 47
A82: HUMAN CAPITAL | B82: Medical / training tech spend | C82: 100000 | D82: 110000 | E82: 130000 | F82: 150000 | G82: 175000 | H82: 185000
A83: HUMAN CAPITAL | B83: Travel logistics ratio (air-heavy) | C83: 0.82 | D83: 0.82 | E83: 0.83 | F83: 0.84 | G83: 0.84 | H83: 0.84
A84: HUMAN CAPITAL | B84: Player housing spend | C84: 200000 | D84: 210000 | E84: 230000 | F84: 250000 | G84: 280000 | H84: 290000
A85: HUMAN CAPITAL | B85: AHL-only salary floor | C85: 49000 | D85: 50000 | E85: 51500 | F85: 52725 | G85: 54000 | H85: 55620
A86: HUMAN CAPITAL | B86: AHL-only average salary | C86: 65000 | D86: 66000 | E86: 70000 | F86: 74000 | G86: 78000 | H86: 80000
A87: HUMAN CAPITAL | B87: Insurance premiums | C87: 200000 | D87: 210000 | E87: 230000 | F87: 250000 | G87: 270000 | H87: 280000
... A96: DIGITAL | B96: Email database value per active subscriber | C96: 5 | D96: 5 | E96: 5 | F96: 5 | G96: 5 | H96: 5

Sheet Master_Model
A1: San Diego Gulls — Forensic Financial, Operational & Marketing Model (FY2021-22 to FY2026-27)
A2: Public numbers are linked back to the Assumptions tab. Private figures are explicitly modeled estimates or logical ranges translated into a base-case value.
A4: ID | B4: Group | C4: Field | D4: Unit | E4: 2021-22 | F4: 2022-23 | G4: 2023-24 | H4: 2024-25 | I4: 2025-26 | J4: 2026-27 | K4: Status | L4: Confidence | M4: Primary Source / Method | N4: Notes
A5: 1. Fan Demand, Schedule & Ticketing
A6: 1 | B6: Fan Demand / Ticketing | C6: Average attendance | D6: fans/game | E6: =Assumptions!C24 | F6: =Assumptions!D24 | G6: =Assumptions!E24 | H6: =Assumptions!F24 | I6: =Assumptions!G24 | J6: =Assumptions!H24 | K6: Public input / projection | L6: High | M6: HockeyDB / official schedule | N6: 2026-27 baseline projected from 2025-26 using control.
A7: 2 | B7: Fan Demand / Ticketing | C7: Home games | D7: games | E7: =Assumptions!C25 | F7: =Assumptions!D25 | G7: =Assumptions!E25 | H7: =Assumptions!F25 | I7: =Assumptions!G25 | J7: =Assumptions!H25 | K7: Public input | L7: High | M7: Official schedules | N7: 2021-22 was 34 home games; subsequent seasons 36.
A8: 3 | B8: Fan Demand / Ticketing | C8: Total home attendance | D8: fans | E8: =E6*E7 | F8: =F6*F7 | G8: =G6*G7 | H8: =H6*H7 | I8: =I6*I7 | J8: =J6*J7 | K8: Derived | L8: High | M8: Attendance × home games | N8: Average attendance multiplied by home games.
A9: 4 | B9: Fan Demand / Ticketing | C9: Home weekend dates | D9: dates | E9: =Assumptions!C28 | F9: =Assumptions!D28 | G9: =Assumptions!E28 | H9: =Assumptions!F28 | I9: =Assumptions!G28 | J9: =Assumptions!H28 | K9: Public input | L9: High | M9: Official schedules | N9: Official yearly schedule releases.
A10: 5 | B10: Fan Demand / Ticketing | C10: Friday home games | D10: games | E10: =Assumptions!C29 | F10: =Assumptions!D29 | G10: =Assumptions!E29 | H10: =Assumptions!F29 | I10: =Assumptions!G29 | J10: =Assumptions!H29 | K10: Public input | L10: High | M10: Official schedules | N10: Official yearly schedule releases.
A11: 6 | B11: Fan Demand / Ticketing | C11: Saturday home games | D11: games | E11: =Assumptions!C30 | F11: =Assumptions!D30 | G11: =Assumptions!E30 | H11: =Assumptions!F30 | I11: =Assumptions!G30 | J11: =Assumptions!H30 | K11: Public input / projection | L11: High | M11: Official schedules | N11: 2026-27 baseline projected mix.
A12: 7 | B12: Fan Demand / Ticketing | C12: Sunday home games | D12: games | E12: =Assumptions!C31 | F12: =Assumptions!D31 | G12: =Assumptions!E31 | H12: =Assumptions!F31 | I12: =Assumptions!G31 | J12: =Assumptions!H31 | K12: Public input / projection | L12: High | M12: Official schedules | N12: 2026-27 baseline projected mix.
A13: 8 | B13: Fan Demand / Ticketing | C13: Back-to-back sets | D13: sets | E13: =Assumptions!C32 | F13: =Assumptions!D32 | G13: =Assumptions!E32 | H13: =Assumptions!F32 | I13: =Assumptions!G32 | J13: =Assumptions!H32 | K13: Public input | L13: High | M13: Official schedules | N13: Official yearly schedule releases.
A14: 9 | B14: Fan Demand / Ticketing | C14: Promotional / theme nights | D14: nights | E14: =Assumptions!C33 | F14: =Assumptions!D33 | G14: =Assumptions!E33 | H14: =Assumptions!F33 | I14: =Assumptions!G33 | J14: =Assumptions!H33 | K14: Public input / projection | L14: High | M14: Official promo releases | N14: 2025-26 includes 8 anniversary nights + 20 additional promotional nights.
A15: 10 | B15: Fan Demand / Ticketing | C15: Giveaway items | D15: items | E15: =Assumptions!C34 | F15: =Assumptions!D34 | G15: =Assumptions!E34 | H15: =Assumptions!F34 | I15: =Assumptions!G34 | J15: =Assumptions!H34 | K15: Public input / projection | L15: Medium | M15: Official promo releases | N15: 2025-26 current public list includes five announced giveaways.
A16: 11 | B16: Fan Demand / Ticketing | C16: Pregame tailgates | D16: events | E16: =Assumptions!C35 | F16: =Assumptions!D35 | G16: =Assumptions!E35 | H16: =Assumptions!F35 | I16: =Assumptions!G35 | J16: =Assumptions!H35 | K16: Public input / projection | L16: Medium | M16: Official promo releases | N16: Counted / projected from public promo schedules.
A17: 12 | B17: Fan Demand / Ticketing | C17: STM entry price | D17: $ | E17: =Assumptions!C36 | F17: =Assumptions!D36 | G17: =Assumptions!E36 | H17: =Assumptions!F36 | I17: =Assumptions!G36 | J17: =Assumptions!H36 | K17: Public input / projection | L17: High | M17: Official ticketing releases | N17: Gulls Elite floor price.
A18: 13 | B18: Fan Demand / Ticketing | C18: STM entry price per game | D18: $ | E18: =IFERROR(E17/E7,0) | F18: =IFERROR(F17/F7,0) | G18: =IFERROR(G17/G7,0) | H18: =IFERROR(H17/H7,0) | I18: =IFERROR(I17/I7,0) | J18: =IFERROR(J17/J7,0) | K18: Derived | L18: High | M18: STM entry price ÷ home games | N18: Season-ticket floor divided by home games.
A19: 14 | B19: Fan Demand / Ticketing | C19: Single-game floor (box office / public) | D19: $ | E19: =Assumptions!C37 | F19: =Assumptions!D37 | G19: =Assumptions!E37 | H19: =Assumptions!F37 | I19: =Assumptions!G37 | J19: =Assumptions!H37 | K19: Public input / estimate / projection | L19: Medium | M19: Official ticketing releases | N19: 2024-25 floor is interpolated estimate.
A20: 15 | B20: Fan Demand / Ticketing | C20: Single-game floor (online incl. fees) | D20: $ | E20: =Assumptions!C38 | F20: =Assumptions!D38 | G20: =Assumptions!E38 | H20: =Assumptions!F38 | I20: =Assumptions!G38 | J20: =Assumptions!H38 | K20: Estimate / projection | L20: Medium | M20: Official 2025-26 ticketing release | N20: 2025-26 is official; 2024-25 and 2026-27 are modeled estimates.
A21: 16 | B21: Fan Demand / Ticketing | C21: College ticket price | D21: $ | E21: =Assumptions!C39 | F21: =Assumptions!D39 | G21: =Assumptions!E39 | H21: =Assumptions!F39 | I21: =Assumptions!G39 | J21: =Assumptions!H39 | K21: Public input / projection | L21: Medium | M21: Official college page | N21: Current season official price.
A22: 17 | B22: Fan Demand / Ticketing | C22: Family pack price floor | D22: $ | E22: =Assumptions!C40 | F22: =Assumptions!D40 | G22: =Assumptions!E40 | H22: =Assumptions!F40 | I22: =Assumptions!G40 | J22: =Assumptions!H40 | K22: Public input / projection | L22: Medium | M22: Official family-pack page | N22: Current-season official product.
A23: 18 | B23: Fan Demand / Ticketing | C23: Group minimum size | D23: tickets | E23: =Assumptions!C41 | F23: =Assumptions!D41 | G23: =Assumptions!E41 | H23: =Assumptions!F41 | I23: =Assumptions!G41 | J23: =Assumptions!H41 | K23: Public / context | L23: Medium | M23: Official group page | N23: Assumed stable historically.
A24: 19 | B24: Fan Demand / Ticketing | C24: Max mini-plan discount | D24: pct | E24: =Assumptions!C42 | F24: =Assumptions!D42 | G24: =Assumptions!E42 | H24: =Assumptions!F42 | I24: =Assumptions!G42 | J24: =Assumptions!H42 | K24: Estimate / projection | L24: Low | M24: Public current mini-plan page | N24: Historical values are conservative placeholders.
A25: 20 | B25: Fan Demand / Ticketing | C25: Weighted average ticket price (modeled) | D25: $ | E25: =Assumptions!C43 | F25: =Assumptions!D43 | G25: =Assumptions!E43 | H25: =Assumptions!F43 | I25: =Assumptions!G43 | J25: =Assumptions!H43 | K25: Estimate / projection | L25: Medium | M25: Model methodology | N25: Modeled from ticket product mix and public price anchors.
A26: 21 | B26: Fan Demand / Ticketing | C26: Group sales share of gate | D26: pct | E26: =Assumptions!C44 | F26: =Assumptions!D44 | G26: =Assumptions!E44 | H26: =Assumptions!F44 | I26: =Assumptions!G44 | J26: =Assumptions!H44 | K26: Estimate / projection | L26: Low | M26: Model methodology | N26: Logical range based on minor-league group channel importance.
A27: 22 | B27: Fan Demand / Ticketing | C27: Premium seating yield | D27: $ | E27: =Assumptions!C45 | F27: =Assumptions!D45 | G27: =Assumptions!E45 | H27: =Assumptions!F45 | I27: =Assumptions!G45 | J27: =Assumptions!H45 | K27: Estimate / projection | L27: Low | M27: Model methodology | N27: Embedded within gate yield; not additive in revenue total.
A28: 23 | B28: Fan Demand / Ticketing | C28: STM base (FSE) | D28: FSE | E28: =Assumptions!C46 | F28: =Assumptions!D46 | G28: =Assumptions!E46 | H28: =Assumptions!F46 | I28: =Assumptions!G46 | J28: =Assumptions!H46 | K28: Estimate / projection | L28: Low | M28: Model methodology | N28: Modeled from attendance and ticket mix.
A29: 24 | B29: Fan Demand / Ticketing | C29: STM retention rate | D29: pct | E29: =Assumptions!C47 | F29: =Assumptions!D47 | G29: =Assumptions!E47 | H29: =Assumptions!F47 | I29: =Assumptions!G47 | J29: =Assumptions!H47 | K29: Estimate / projection | L29: Low | M29: Model methodology | N29: Modeled range.
A30: 2. Revenue Engine & Economics
A31: 25 | B31: Revenue Engine | C31: Gate revenue | D31: $ | E31: =E8*E25 | F31: =F8*F25 | G31: =G8*G25 | H31: =H8*H25 | I31: =I8*I25 | J31: =J8*J25 | K31: Derived | L31: Medium | M31: Total attendance × WATP | N31: Modeled gate revenue using weighted average ticket price.
A32: 26 | B32: Revenue Engine | C32: Facility fee per paid ticket | D32: $ | E32: =Assumptions!C68 | F32: =Assumptions!D68 | G32: =Assumptions!E68 | H32: =Assumptions!F68 | I32: =Assumptions!G68 | J32: =Assumptions!H68 | K32: Estimate | L32: Low | M32: Lease-era reporting / model assumption | N32: Publicly discussed current surcharge structure; early years not confirmed.
A33: 27 | B33: Revenue Engine | C33: Facility fee liability | D33: $ | E33: =IFERROR(E8*E32,"") | F33: =IFERROR(F8*F32,"") | G33: =IFERROR(G8*G32,"") | H33: =IFERROR(H8*H32,"") | I33: =IFERROR(I8*I32,"") | J33: =IFERROR(J8*J32,"") | K33: Derived | L33: Low | M33: Total attendance × facility fee | N33: Pass-through city/venue fee liability estimate.
A34: 28 | B34: Revenue Engine | C34: Revenue per available seat (RevPAS) | D34: $ | E34: =IFERROR(E31/(E56*E7),"") | F34: =IFERROR(F31/(F56*F7),"") | G34: =IFERROR(G31/(G56*G7),"") | H34: =IFERROR(H31/(H56*H7),"") | I34: =IFERROR(I31/(I56*I7),"") | J34: =IFERROR(J31/(J56*J7),"") | K34: Derived | L34: Medium | M34: Gate ÷ (capacity × home games) | N34: Uses 12,920 hockey capacity.
A35: 29 | B35: Revenue Engine | C35: F&B per-cap gross | D35: $ | E35: =Assumptions!C48 | F35: =Assumptions!D48 | G35: =Assumptions!E48 | H35: =Assumptions!F48 | I35: =Assumptions!G48 | J35: =Assumptions!H48 | K35: Estimate / projection | L35: Low | M35: Model methodology | N35: Gross in-building spend, not team net.
A36: 30 | B36: Revenue Engine | C36: Team concession commission rate | D36: pct | E36: =Assumptions!C49 | F36: =Assumptions!D49 | G36: =Assumptions!E49 | H36: =Assumptions!F49 | I36: =Assumptions!G49 | J36: =Assumptions!H49 | K36: Estimate | L36: Low | M36: Model methodology | N36: Private split; modeled nominal rate.
A37: 31 | B37: Revenue Engine | C37: Concession commission revenue | D37: $ | E37: =E8*E35*E36 | F37: =F8*F35*F36 | G37: =G8*G35*G36 | H37: =H8*H35*H36 | I37: =I8*I35*I36 | J37: =J8*J35*J36 | K37: Derived | L37: Low | M37: Attendance × F&B per-cap × commission rate | N37: Team-side concession revenue estimate.
A38: 32 | B38: Revenue Engine | C38: Merchandise per-cap | D38: $ | E38: =Assumptions!C50 | F38: =Assumptions!D50 | G38: =Assumptions!E50 | H38: =Assumptions!F50 | I38: =Assumptions!G50 | J38: =Assumptions!H50 | K38: Estimate / projection | L38: Low | M38: Model methodology | N38: Modeled team-store spend per attendee.
A39: 33 | B39: Revenue Engine | C39: Merchandise revenue | D39: $ | E39: =E8*E38 | F39: =F8*F38 | G39: =G8*G38 | H39: =H8*H38 | I39: =I8*I38 | J39: =J8*J38 | K39: Derived | L39: Low | M39: Attendance × merch per-cap | N39: Modeled gross merchandise revenue.
A40: 34 | B40: Revenue Engine | C40: Parking fee assumption | D40: $ | E40: =Assumptions!C51 | F40: =Assumptions!D51 | G40: =Assumptions!E51 | H40: =Assumptions!F51 | I40: =Assumptions!G51 | J40: =Assumptions!H51 | K40: Estimate / projection | L40: Low | M40: Public parking page + model | N40: Event-specific public fee structure; year values are model anchors.
A41: 35 | B41: Revenue Engine | C41: Average auto occupancy | D41: persons | E41: =Assumptions!C52 | F41: =Assumptions!D52 | G41: =Assumptions!E52 | H41: =Assumptions!F52 | I41: =Assumptions!G52 | J41: =Assumptions!H52 | K41: Estimate | L41: Low | M41: Model methodology | N41: Transport assumption for parking yield.
A42: 36 | B42: Revenue Engine | C42: Team share of parking | D42: pct | E42: =Assumptions!C53 | F42: =Assumptions!D53 | G42: =Assumptions!E53 | H42: =Assumptions!F53 | I42: =Assumptions!G53 | J42: =Assumptions!H53 | K42: Estimate | L42: Low | M42: Model methodology | N42: No public split located; nominal placeholder only.
A43: 37 | B43: Revenue Engine | C43: Parking revenue yield | D43: $ | E43: =IFERROR((E8/E41)*E40*E42,"") | F43: =IFERROR((F8/F41)*F40*F42,"") | G43: =IFERROR((G8/G41)*G40*G42,"") | H43: =IFERROR((H8/H41)*H40*H42,"") | I43: =IFERROR((I8/I41)*I40*I42,"") | J43: =IFERROR((J8/J41)*J40*J42,"") | K43: Derived | L43: Low | M43: Attendance ÷ occupancy × fee × share | N43: Team-side parking estimate.
A44: 38 | B44: Revenue Engine | C44: Total per-cap spend (F&B + merch) | D44: $ | E44: =E35+E38 | F44: =F35+F38 | G44: =G35+G38 | H44: =H35+H38 | I44: =I35+I38 | J44: =J35+J38 | K44: Derived | L44: Low | M44: F&B per-cap + merch per-cap | N44: Gross fan spend indicator.
A45: 39 | B45: Revenue Engine | C45: Total sponsorship revenue | D45: $ | E45: =Assumptions!C54 | F45: =Assumptions!D54 | G45: =Assumptions!E54 | H45: =Assumptions!F54 | I45: =Assumptions!G54 | J45: =Assumptions!H54 | K45: Estimate / projection | L45: Low | M45: Model methodology | N45: Total sponsorship / partner inventory revenue.
A46: 40 | B46: Revenue Engine | C46: Title partner value | D46: $ | E46: =Assumptions!C55 | F46: =Assumptions!D55 | G46: =Assumptions!E55 | H46: =Assumptions!F55 | I46: =Assumptions!G55 | J46: =Assumptions!H55 | K46: Estimate | L46: Low | M46: Model methodology | N46: Subcomponent of sponsorship total.
A47: 41 | B47: Revenue Engine | C47: Jersey / patch revenue | D47: $ | E47: =Assumptions!C56 | F47: =Assumptions!D56 | G47: =Assumptions!E56 | H47: =Assumptions!F56 | I47: =Assumptions!G56 | J47: =Assumptions!H56 | K47: Estimate | L47: Low | M47: Model methodology | N47: Subcomponent of sponsorship total.
A48: 42 | B48: Revenue Engine | C48: Digital inventory yield | D48: $ | E48: =Assumptions!C57 | F48: =Assumptions!D57 | G48: =Assumptions!E57 | H48: =Assumptions!F57 | I48: =Assumptions!G57 | J48: =Assumptions!H57 | K48: Estimate | L48: Low | M48: Model methodology | N48: Subcomponent of sponsorship total.
A49: 43 | B49: Revenue Engine | C49: Other sponsorship revenue | D49: $ | E49: =E45-E46-E47-E48 | F49: =F45-F46-F47-F48 | G49: =G45-G46-G47-G48 | H49: =H45-H46-H47-H48 | I49: =I45-I46-I47-I48 | J49: =J45-J46-J47-J48 | K49: Derived | L49: Low | M49: Residual sponsorship value | N49: Total sponsorship less title, patch, and digital subcomponents.
A50: 44 | B50: Revenue Engine | C50: Broadcast / streaming value | D50: $ | E50: =Assumptions!C58 | F50: =Assumptions!D58 | G50: =Assumptions!E58 | H50: =Assumptions!F58 | I50: =Assumptions!G58 | J50: =Assumptions!H58 | K50: Estimate | L50: Low | M50: AHL/FloHockey + local TV context | N50: Modeled media value.
A51: 45 | B51: Revenue Engine | C51: Youth hockey / camp revenue | D51: $ | E51: =Assumptions!C91 | F51: =Assumptions!D91 | G51: =Assumptions!E91 | H51: =Assumptions!F91 | I51: =Assumptions!G91 | J51: =Assumptions!H91 | K51: Estimate | L51: Low | M51: Model methodology | N51: Direct ecosystem youth / camp estimate.
A52: 46 | B52: Revenue Engine | C52: Gross annual revenue | D52: $ | E52: =IFERROR(E31+E37+E39+E43+E45+E50+E51,0) | F52: =IFERROR(F31+F37+F39+F43+F45+F50+F51,0) | G52: =IFERROR(G31+G37+G39+G43+G45+G50+G51,0) | H52: =IFERROR(H31+H37+H39+H43+H45+H50+H51,0) | I52: =IFERROR(I31+I37+I39+I43+I45+I50+I51,0) | J52: =IFERROR(J31+J37+J39+J43+J45+J50+J51,0) | K52: Derived | L52: Medium | M52: Gate + commission + merch + parking + sponsorship + media + youth | N52: Excludes NHL parent subsidy to preserve stand-alone club revenue view.
A53: 47 | B53: Revenue Engine | C53: NHL parent subsidy | D53: $ | E53: =Assumptions!C90 | F53: =Assumptions!D90 | G53: =Assumptions!E90 | H53: =Assumptions!F90 | I53: =Assumptions!G90 | J53: =Assumptions!H90 | K53: Estimate | L53: Low | M53: Model methodology | N53: Anaheim Ducks affiliate support estimate.
A54: 48 | B54: Revenue Engine | C54: Operating resources incl. parent support | D54: $ | E54: =E52+E53 | F54: =F52+F53 | G54: =G52+G53 | H54: =H52+H53 | I54: =I52+I53 | J54: =J52+J53 | K54: Derived | L54: Low | M54: Gross revenue + parent subsidy | N54: Useful for full operating-scale context.
A55: 3. Arena, Municipal & Venue Footprint
A56: 49 | B56: Arena / Municipal | C56: Hockey seating capacity | D56: seats | E56: =Assumptions!C26 | F56: =Assumptions!D26 | G56: =Assumptions!E26 | H56: =Assumptions!F26 | I56: =Assumptions!G26 | J56: =Assumptions!H26 | K56: Context | L56: Medium | M56: Official media guide | N56: Capacity used in RevPAS.
A57: 50 | B57: Arena / Municipal | C57: General venue capacity | D57: seats | E57: =Assumptions!C27 | F57: =Assumptions!D27 | G57: =Assumptions!E27 | H57: =Assumptions!F27 | I57: =Assumptions!G27 | J57: =Assumptions!H27 | K57: Public | L57: High | M57: Official venue page | N57: Current listed arena capacity.
A58: 51 | B58: Arena / Municipal | C58: Base rent floor (annualized) | D58: $ | E58: =Assumptions!C69 | F58: =Assumptions!D69 | G58: =Assumptions!E69 | H58: =Assumptions!F69 | I58: =Assumptions!G69 | J58: =Assumptions!H69 | K58: Public / projection | L58: Medium | M58: Arena lease reporting | N58: Arena-operator level, not disclosed team sublease.
A59: 52 | B59: Arena / Municipal | C59: Rent escalator | D59: pct | E59: =Assumptions!C70 | F59: =Assumptions!D70 | G59: =Assumptions!E70 | H59: =Assumptions!F70 | I59: =Assumptions!G70 | J59: =Assumptions!H70 | K59: Derived / projection | L59: Medium | M59: Lease floor progression | N59: Derived from public operator-level rent floor.
A60: 53 | B60: Arena / Municipal | C60: Security / police overhead per event | D60: $ | E60: =Assumptions!C71 | F60: =Assumptions!D71 | G60: =Assumptions!E71 | H60: =Assumptions!F71 | I60: =Assumptions!G71 | J60: =Assumptions!H71 | K60: Estimate | L60: Low | M60: City event policing framework | N60: Event cost estimate.
A61: 54 | B61: Arena / Municipal | C61: Security / police overhead (annual) | D61: $ | E61: =E60*E7 | F61: =F60*F7 | G61: =G60*G7 | H61: =H60*H7 | I61: =I60*I7 | J61: =J60*J7 | K61: Derived | L61: Low | M61: Per-event security × home games | N61: Annualized event security cost.
A62: 55 | B62: Arena / Municipal | C62: Utilities & HVAC load | D62: $ | E62: =Assumptions!C72 | F62: =Assumptions!D72 | G62: =Assumptions!E72 | H62: =Assumptions!F72 | I62: =Assumptions!G72 | J62: =Assumptions!H72 | K62: Estimate | L62: Low | M62: Model methodology | N62: Annualized utilities / ice / cooling.
A63: 56 | B63: Arena / Municipal | C63: Load-in / load-out allocation | D63: $ | E63: =Assumptions!C73 | F63: =Assumptions!D73 | G63: =Assumptions!E73 | H63: =Assumptions!F73 | I63: =Assumptions!G73 | J63: =Assumptions!H73 | K63: Estimate | L63: Low | M63: Model methodology | N63: Annualized mixed-use arena conversion allocation.
A64: 57 | B64: Arena / Municipal | C64: Midway district assessment / CFD | D64: $ | E64: =Assumptions!C74 | F64: =Assumptions!D74 | G64: =Assumptions!E74 | H64: =Assumptions!F74 | I64: =Assumptions!G74 | J64: =Assumptions!H74 | K64: Context | L64: Low | M64: Public review | N64: No public team-side assessment identified.
A65: 58 | B65: Arena / Municipal | C65: Lease horizon (months remaining) | D65: months | E65: =Assumptions!C75 | F65: =Assumptions!D75 | G65: =Assumptions!E75 | H65: =Assumptions!F75 | I65: =Assumptions!G75 | J65: =Assumptions!H75 | K65: Estimate | L65: Low | M65: Midway Rising timeline | N65: Directional planning metric only.
A66: 59 | B66: Arena / Municipal | C66: Naming-rights tranche allocable to team ops | D66: $ | E66: =Assumptions!C76 | F66: =Assumptions!D76 | G66: =Assumptions!E76 | H66: =Assumptions!F76 | I66: =Assumptions!G76 | J66: =Assumptions!H76 | K66: Estimate | L66: Low | M66: Model methodology | N66: Logical annual value attributed to team ops.
A67: 60 | B67: Arena / Municipal | C67: Tax liability | D67: $ | E67: =Assumptions!C77 | F67: =Assumptions!D77 | G67: =Assumptions!E77 | H67: =Assumptions!F77 | I67: =Assumptions!G77 | J67: =Assumptions!H77 | K67: Estimate | L67: Low | M67: Model methodology | N67: Nominal local tax placeholder.
A68: 61 | B68: Arena / Municipal | C68: Debt-to-value ratio | D68: pct | E68: =Assumptions!C78 | F68: =Assumptions!D78 | G68: =Assumptions!E78 | H68: =Assumptions!F78 | I68: =Assumptions!G78 | J68: =Assumptions!H78 | K68: Estimate | L68: Low | M68: Model methodology | N68: Nominal placeholder only.
A69: 4. Hockey Ops, Organization & Human Capital
A70: 62 | B70: Human Capital | C70: Roster headcount | D70: players | E70: =Assumptions!C79 | F70: =Assumptions!D79 | G70: =Assumptions!E79 | H70: =Assumptions!F79 | I70: =Assumptions!G79 | J70: =Assumptions!H79 | K70: Public / projection | L70: Medium | M70: Official roster / game notes | N70: Opening-night/current roster anchor.
A71: 63 | B71: Human Capital | C71: Coaching staff payroll | D71: $ | E71: =Assumptions!C80 | F71: =Assumptions!D80 | G71: =Assumptions!E80 | H71: =Assumptions!F80 | I71: =Assumptions!G80 | J71: =Assumptions!H80 | K71: Estimate | L71: Low | M71: Model methodology | N71: Head coach + assistants + video support.
A72: 64 | B72: Human Capital | C72: Front office FTE | D72: FTE | E72: =Assumptions!C81 | F72: =Assumptions!D81 | G72: =Assumptions!E81 | H72: =Assumptions!F81 | I72: =Assumptions!G81 | J72: =Assumptions!H81 | K72: Estimate | L72: Medium | M72: Official front office + LinkedIn | N72: Business / marketing / partnership staff estimate.
A73: 65 | B73: Human Capital | C73: Medical / training tech spend | D73: $ | E73: =Assumptions!C82 | F73: =Assumptions!D82 | G73: =Assumptions!E82 | H73: =Assumptions!F82 | I73: =Assumptions!G82 | J73: =Assumptions!H82 | K73: Estimate | L73: Low | M73: Model methodology | N73: Sports science / recovery allocation.
A74: 66 | B74: Human Capital | C74: Travel logistics ratio (air-heavy) | D74: pct | E74: =Assumptions!C83 | F74: =Assumptions!D83 | G74: =Assumptions!E83 | H74: =Assumptions!F83 | I74: =Assumptions!G83 | J74: =Assumptions!H83 | K74: Estimate | L74: Low | M74: Model methodology | N74: Travel intensity ratio.
A75: 67 | B75: Human Capital | C75: Player housing spend | D75: $ | E75: =Assumptions!C84 | F75: =Assumptions!D84 | G75: =Assumptions!E84 | H75: =Assumptions!F84 | I75: =Assumptions!G84 | J75: =Assumptions!H84 | K75: Estimate | L75: Low | M75: Model methodology | N75: Local market housing support estimate.
A76: 68 | B76: Human Capital | C76: AHL-only salary floor | D76: $ | E76: =Assumptions!C85 | F76: =Assumptions!D85 | G76: =Assumptions!E85 | H76: =Assumptions!F85 | I76: =Assumptions!G85 | J76: =Assumptions!H85 | K76: Estimate / projection | L76: Medium | M76: PHPA / benchmark | N76: 2024-25 visible minimum, other years stepped.
A77: 69 | B77: Human Capital | C77: AHL-only average salary | D77: $ | E77: =Assumptions!C86 | F77: =Assumptions!D86 | G77: =Assumptions!E86 | H77: =Assumptions!F86 | I77: =Assumptions!G86 | J77: =Assumptions!H86 | K77: Estimate | L77: Low | M77: Model methodology | N77: Modeled non-NHL salary average.
A78: 70 | B78: Human Capital | C78: Insurance premiums | D78: $ | E78: =Assumptions!C87 | F78: =Assumptions!D87 | G78: =Assumptions!E87 | H78: =Assumptions!F87 | I78: =Assumptions!G87 | J78: =Assumptions!H87 | K78: Estimate | L78: Low | M78: Model methodology | N78: Workers' comp / liability allocation.
A79: 71 | B79: Human Capital | C79: Equipment lifecycle cost | D79: $ | E79: =Assumptions!C88 | F79: =Assumptions!D88 | G79: =Assumptions!E88 | H79: =Assumptions!F88 | I79: =Assumptions!G88 | J79: =Assumptions!H88 | K79: Estimate | L79: Low | M79: Model methodology | N79: Annual equipment budget estimate.
A80: 72 | B80: Human Capital | C80: Ducks prospects in San Diego | D80: players | E80: =Assumptions!C89 | F80: =Assumptions!D89 | G80: =Assumptions!E89 | H80: =Assumptions!F89 | I80: =Assumptions!G89 | J80: =Assumptions!H89 | K80: Estimate | L80: Low | M80: Official roster/game notes | N80: Approximate Ducks-controlled development pipeline.
A81: 5. Digital, Marketing & Brand Equity
A82: 73 | B82: Digital / Brand | C82: Email subscribers (estimated active) | D82: subs | E82: =Assumptions!C59 | F82: =Assumptions!D59 | G82: =Assumptions!E59 | H82: =Assumptions!F59 | I82: =Assumptions!G59 | J82: =Assumptions!H59 | K82: Estimate | L82: Low | M82: Model methodology | N82: Owned-contact base estimate.
A83: 74 | B83: Digital / Brand | C83: Email database value per active subscriber | D83: $ | E83: =Assumptions!C96 | F83: =Assumptions!D96 | G83: =Assumptions!E96 | H83: =Assumptions!F96 | I83: =Assumptions!G96 | J83: =Assumptions!H96 | K83: Control | L83: Medium | M83: User assumption | N83: User-directed valuation heuristic.
A84: 75 | B84: Digital / Brand | C84: Email database value | D84: $ | E84: =E82*E83 | F84: =F82*F83 | G84: =G82*G83 | H84: =H82*H83 | I84: =I82*I83 | J84: =J82*J83 | K84: Derived | L84: Low | M84: Email subs × $5 heuristic | N84: Simple database value proxy.
A85: 76 | B85: Digital / Brand | C85: Social audience (aggregate est.) | D85: followers | E85: =Assumptions!C60 | F85: =Assumptions!D60 | G85: =Assumptions!E60 | H85: =Assumptions!F60 | I85: =Assumptions!G60 | J85: =Assumptions!H60 | K85: Estimate | L85: Low | M85: Public social snippets | N85: Approximate total audience across major platforms.
A86: 77 | B86: Digital / Brand | C86: Website monthly visits | D86: visits | E86: =Assumptions!C61 | F86: =Assumptions!D61 | G86: =Assumptions!E61 | H86: =Assumptions!F61 | I86: =Assumptions!G61 | J86: =Assumptions!H61 | K86: Estimate / projection | L86: Medium | M86: Similarweb | N86: Current-year anchor plus historical trend/projection.
A87: 78 | B87: Digital / Brand | C87: Bounce rate | D87: pct | E87: =Assumptions!C62 | F87: =Assumptions!D62 | G87: =Assumptions!E62 | H87: =Assumptions!F62 | I87: =Assumptions!G62 | J87: =Assumptions!H62 | K87: Estimate / projection | L87: Medium | M87: Similarweb | N87: Current-year anchor plus trend.
A88: 79 | B88: Digital / Brand | C88: Pages per visit | D88: pages | E88: =Assumptions!C63 | F88: =Assumptions!D63 | G88: =Assumptions!E63 | H88: =Assumptions!F63 | I88: =Assumptions!G63 | J88: =Assumptions!H63 | K88: Estimate / projection | L88: Medium | M88: Similarweb | N88: Current-year anchor plus trend.
A89: 80 | B89: Digital / Brand | C89: Average visit duration (sec) | D89: sec | E89: =Assumptions!C64 | F89: =Assumptions!D64 | G89: =Assumptions!E64 | H89: =Assumptions!F64 | I89: =Assumptions!G64 | J89: =Assumptions!H64 | K89: Estimate / projection | L89: Medium | M89: Similarweb | N89: Current-year anchor plus trend.
A90: 81 | B90: Digital / Brand | C90: Organic search share | D90: pct | E90: =Assumptions!C65 | F90: =Assumptions!D65 | G90: =Assumptions!E65 | H90: =Assumptions!F65 | I90: =Assumptions!G65 | J90: =Assumptions!H65 | K90: Estimate / projection | L90: Medium | M90: Similarweb | N90: Current-year anchor plus trend.
A91: 82 | B91: Digital / Brand | C91: Customer acquisition cost | D91: $ | E91: =Assumptions!C66 | F91: =Assumptions!D66 | G91: =Assumptions!E66 | H91: =Assumptions!F66 | I91: =Assumptions!G66 | J91: =Assumptions!H66 | K91: Estimate | L91: Low | M91: Model methodology | N91: Per-new-buyer marketing cost estimate.
A92: 83 | B92: Digital / Brand | C92: Net promoter score | D92: pts | E92: =Assumptions!C67 | F92: =Assumptions!D67 | G92: =Assumptions!E67 | H92: =Assumptions!F67 | I92: =Assumptions!G67 | J92: =Assumptions!H67 | K92: Estimate | L92: Low | M92: Model methodology | N92: Sentiment proxy, not official survey.
A93: 84 | B93: Digital / Brand | C93: Foundation asset base | D93: $ | E93: =Assumptions!C92 | F93: =Assumptions!D92 | G93: =Assumptions!E92 | H93: =Assumptions!F92 | I93: =Assumptions!G92 | J93: =Assumptions!H92 | K93: Estimate | L93: Low | M93: Official foundation giving + model | N93: Logical asset placeholder.
A94: 85 | B94: Digital / Brand | C94: Affiliate synergy value | D94: $ | E94: =Assumptions!C93 | F94: =Assumptions!D93 | G94: =Assumptions!E93 | H94: =Assumptions!F93 | I94: =Assumptions!G93 | J94: =Assumptions!H93 | K94: Estimate | L94: Low | M94: Model methodology | N94: Ducks ecosystem cross-promotional value.
A95: 86 | B95: Digital / Brand | C95: Trademark / brand asset value | D95: $ | E95: =Assumptions!C94 | F95: =Assumptions!D94 | G95: =Assumptions!E94 | H95: =Assumptions!F94 | I95: =Assumptions!G94 | J95: =Assumptions!H94 | K95: Estimate | L95: Low | M95: Model methodology | N95: Logical brand asset placeholder.
A96: 6. Profitability, Efficiency & Valuation
A97: 87 | B97: Valuation | C97: EBITDA margin | D97: pct | E97: =IFERROR(E98/E52,0) | F97: =IFERROR(F98/F52,0) | G97: =IFERROR(G98/G52,0) | H97: =IFERROR(H98/H52,0) | I97: =IFERROR(I98/I52,0) | J97: =IFERROR(J98/J52,0) | K97: Derived | L97: Medium | M97: Modeled margin from cost stack | N97: Calculated from EBITDA ÷ gross revenue.
A98: 88 | B98: Valuation | C98: EBITDA | D98: $ | E98: =IFERROR(E52-E99,0) | F98: =IFERROR(F52-F99,0) | G98: =IFERROR(G52-G99,0) | H98: =IFERROR(H52-H99,0) | I98: =IFERROR(I52-I99,0) | J98: =IFERROR(J52-J99,0) | K98: Derived | L98: Medium | M98: Gross revenue less modeled operating cost stack | N98: Operating earnings proxy excluding parent subsidy.
A99: 89 | B99: Valuation | C99: Operating expenses (modeled) | D99: $ | E99: =ROUND(E58+E61+E62+E63+E71+(E72*90000)+E73+E75+E78+E79+E67+(E52*0.22),0) | F99: =ROUND(F58+F61+F62+F63+F71+(F72*90000)+F73+F75+F78+F79+F67+(F52*0.22),0) | G99: =ROUND(G58+G61+G62+G63+G71+(G72*90000)+G73+G75+G78+G79+G67+(G52*0.22),0) | H99: =ROUND(H58+H61+H62+H63+H71+(H72*90000)+H73+H75+H78+H79+H67+(H52*0.22),0) | I99: =ROUND(I58+I61+I62+I63+I71+(I72*90000)+I73+I75+I78+I79+I67+(I52*0.22),0) | J99: =ROUND(J58+J61+J62+J63+J71+(J72*90000)+J73+J75+J78+J79+J67+(J52*0.22),0) | K99: Derived | L99: Medium | M99: Modeled cost stack | N99: Includes base rent, security, utilities, load-in, coaching, FO, medical, travel/housing proxy, insurance, equipment, tax, and other overhead.
A100: 90 | B100: Valuation | C100: Operating expense ratio | D100: pct | E100: =IFERROR(E99/E52,0) | F100: =IFERROR(F99/F52,0) | G100: =IFERROR(G99/G52,0) | H100: =IFERROR(H99/H52,0) | I100: =IFERROR(I99/I52,0) | J100: =IFERROR(J99/J52,0) | K100: Derived | L100: Medium | M100: OpEx ÷ gross revenue | N100: Team-level modeled expense ratio.
A101: 91 | B101: Valuation | C101: Revenue multiple | D101: x | E101: =Assumptions!C95 | F101: =Assumptions!D95 | G101: =Assumptions!E95 | H101: =Assumptions!F95 | I101: =Assumptions!G95 | J101: =Assumptions!H95 | K101: Control | L101: Medium | M101: User assumption | N101: Valuation multiple.
...

Sheet Scenario_OnePager
A1: 2026-27 Scenario One-Page Assessment
A2: Interactive planning tab: selected scenario drives the full workbook; this page shows the levers that move revenue, EBITDA, valuation, and demand.
A3: Selected Revenue | D3: Selected EBITDA | G3: Selected Valuation | J3: Selected Attendance | M3: Scenario
A4: =IFERROR(Master_Model!$J$52,0) | D4: =IFERROR(Master_Model!$J$98,0) | G4: =IFERROR(Master_Model!$J$102,0) | J4: =IFERROR(Master_Model!$J$6,0) | M4: =Executive_Dashboard!$C$3
A10: Lever | B10: Baseline | C10: Tactical Upside | D10: Aggressive Growth | E10: Strategic Operational Impact
A11: Attendance Uplift | B11: +3% | C11: +6% | D11: +9% | E11: Leverage San Diego’s veteran and active-duty population with military nights, referral loops, and community endurance-style activations to lift mid-week volume.
A12: Ticket Yield / WATP | B12: +3.2% | C12: +5.0% | D12: +7.5% | E12: Tighten dynamic pricing around Friday/Saturday demand, anniversary games, and premium seat clusters while keeping entry products accessible.
A13: Sponsorship Yield | B13: +9.3% | C13: +12.0% | D13: +16.0% | E13: Bundle digital, theme-night, signage, and hospitality inventory into fewer, higher-value packages with clearer audience data.
A14: F&B Per-Cap | B14: +3.2% | C14: +5.0% | D14: +7.0% | E14: Use Stella Lounge, tailgate, and bundle mechanics to lift mix and spend instead of relying on raw attendance alone.
A15: Merch Conversion | B15: +4.4% | C15: +6.0% | D15: +8.0% | E15: Deploy event-night capsules, auctioned specialty product, and QR-based game-night offers to improve same-visit conversion.
A16: Digital Funnel | B16: +8.0% traffic | C16: +12.0% traffic | D16: +16.0% traffic | E16: Segment email/SMS, simplify mobile landing pages, and retarget first-time buyers into flex-plan, college, and group follow-up journeys.
H20: Team | I20: 2025-26 Attendance | J20: Ticket Entry Anchor | K20: Modeled WATP
H21: San Diego Gulls | I21: 7403 | J21: $23 box office / $28.75 online | K21: 25.4
H22: Coachella Valley Firebirds | I22: 9805 | J22: Premium-heavy desert market / individual-game on-sale | K22: 29.5
H23: Henderson Silver Knights | I23: 4856 | J23: Value nights + group savings up to 40% | K23: 23
H25: Benchmark note: non-Gulls WATP values are directional estimates using public ticket products, market positioning, and attendance context—not disclosed team financials.

Sheet Source_Log
A1: Metric | B1: Category | C1: 2021-22 | D1: 2022-23 | E1: 2023-24 | F1: 2024-25 | G1: 2025-26 | H1: 2026-27 | I1: Unit | J1: Source / Method | K1: Status
A2: 2026-27 attendance growth assumption | B2: CONTROL | H2: 0.03 | I2: pct | J2: Model control | K2: Control
A3: 2026-27 WATP growth assumption | B3: CONTROL | H3: 0.032 | I3: pct | J3: Model control | K3: Control
A4: 2026-27 sponsorship growth assumption | B4: CONTROL | H4: 0.093 | I4: pct | J4: Model control | K4: Control
A5: 2026-27 per-cap F&B growth assumption | B5: CONTROL | H5: 0.032 | I5: pct | J5: Model control | K5: Control
A6: 2026-27 merch per-cap growth assumption | B6: CONTROL | H6: 0.044 | I6: pct | J6: Model control | K6: Control
A7: 2026-27 STM price growth assumption | B7: CONTROL | H7: 0.03 | I7: pct | J7: Model control | K7: Control
A8: 2026-27 single-game price growth assumption | B8: CONTROL | H8: 0.043 | I8: pct | J8: Model control | K8: Control
A9: 2026-27 website traffic growth assumption | B9: CONTROL | H9: 0.08 | I9: pct | J9: Model control | K9: Control
A10: Average attendance | B10: ATTENDANCE | C10: 6992 | D10: 6953 | E10: 7249 | F10: 7262 | G10: 7403 | I10: fans/game | J10: https://www.hockeydb.com/stte/san-diego-gulls-11619.html | K10: Public/Projection
A11: Home games | B11: ATTENDANCE | C11: 34 | D11: 36 | E11: 36 | F11: 36 | G11: 36 | H11: 36 | I11: games | J11: https://www.sandiegogulls.com/news/detail/san-diego-gulls-2021-22-schedule-announced | K11: Public
A12: Hockey seating capacity | B12: VENUE | C12: 12920 | D12: 12920 | E12: 12920 | F12: 12920 | G12: 12920 | H12: 12920 | I12: seats | J12: https://www.sandiegogulls.com/assets/doc/2021-22-San-Diego-Gulls-Media-Guide-compressed-92470e4558.pdf | K12: Context
A13: General venue capacity | B13: VENUE | C13: 14000 | D13: 14000 | E13: 14000 | F13: 14000 | G13: 14000 | H13: 14000 | I13: seats | J13: https://pechangaarenasd.com/about/ | K13: Public
A14: Home weekend dates | B14: SCHEDULE | C14: 23 | D14: 23 | E14: 26 | F14: 25 | G14: 25 | H14: 25 | I14: dates | J14: Multiple official schedule releases on sandiegogulls.com | K14: Public
A15: Friday home games | B15: SCHEDULE | C15: 11 | D15: 12 | E15: 12 | F15: 9 | G15: 10 | H15: 10 | I15: games | J15: Multiple official schedule releases on sandiegogulls.com | K15: Public
A16: Saturday home games | B16: SCHEDULE | C16: 11 | D16: 11 | E16: 12 | F16: 14 | G16: 10 | H16: 11 | I16: games | J16: Multiple official schedule releases on sandiegogulls.com | K16: Public/Projection
A17: Sunday home games | B17: SCHEDULE | C17: 1 | D17: 1 | E17: 2 | F17: 2 | G17: 5 | H17: 4 | I17: games | J17: Multiple official schedule releases on sandiegogulls.com | K17: Public/Projection
A18: Back-to-back sets | B18: SCHEDULE | C18: 24 | D18: 21 | E18: 18 | F18: 20 | G18: 22 | H18: 22 | I18: sets | J18: Multiple official schedule releases on sandiegogulls.com | K18: Public
A19: Promotional/theme nights announced | B19: MARKETING | C19: 13 | D19: 15 | E19: 16 | F19: 23 | G19: 28 | H19: 30 | I19: nights | J19: Multiple official promo releases on sandiegogulls.com | K19: Public/Projection
A20: Giveaway items announced | B20: MARKETING | C20: 7 | D20: 6 | E20: 10 | F20: 11 | G20: 5 | H20: 6 | I20: items | J20: Multiple official promo releases on sandiegogulls.com | K20: Public/Projection
A21: Pregame tailgates | B21: MARKETING | C21: 6 | D21: 6 | E21: 7 | F21: 7 | G21: 7 | H21: 8 | I21: events | J21: Multiple official promo releases on sandiegogulls.com | K21: Public/Projection
A22: STM entry price | B22: TICKETING | C22: 476 | D22: 540 | E22: 540 | F22: 560 | G22: 614 | I22: $/seat | J22: Multiple official ticketing releases on sandiegogulls.com | K22: Public/Projection
A23: Single-game floor (box office / public) | B23: TICKETING | C23: 19 | D23: 21 | E23: 20 | F23: 22 | G23: 23 | I23: $/ticket | J23: Multiple official ticketing releases on sandiegogulls.com | K23: Public/Estimate/Projection
A24: Single-game floor (online incl. fees) | B24: TICKETING | F24: 27.5 | G24: 28.75 | H24: 29.75 | I24: $/ticket | J24: https://www.sandiegogulls.com/news/detail/single-game-tickets-available-now | K24: Estimate/Projection
A25: College ticket price | B25: TICKETING | G25: 17 | H25: 17.5 | I25: $/ticket | J25: https://www.sandiegogulls.com/tickets/college | K25: Public/Projection
A26: Family pack price floor | B26: TICKETING | G26: 130 | H26: 135 | I26: $/pack | J26: https://www.sandiegogulls.com/tickets/4-packs | K26: Public/Projection
A27: Group minimum size | B27: TICKETING | C27: 10 | D27: 10 | E27: 10 | F27: 10 | G27: 10 | H27: 10 | I27: tickets | J27: https://www.sandiegogulls.com/tickets/group-tickets | K27: Public/Context
A28: Max mini-plan discount | B28: TICKETING | C28: 0.15 | D28: 0.15 | E28: 0.2 | F28: 0.3 | G28: 0.3 | H28: 0.3 | I28: pct | J28: https://www.sandiegogulls.com/tickets/gulls-mini-plans | K28: Estimate/Projection
A29: Weighted average ticket price (modeled) | B29: TICKETING | C29: 22 | D29: 22.4 | E29: 23.4 | F29: 24.4 | G29: 25.4 | I29: $/ticket | J29: Model methodology | K29: Estimate/Projection
A30: Group sales share of gate | B30: TICKETING | C30: 0.16 | D30: 0.17 | E30: 0.18 | F30: 0.19 | G30: 0.2 | H30: 0.21 | I30: pct | J30: Model methodology | K30: Estimate/Projection
A31: Premium seating yield (included in gate) | B31: TICKETING | C31: 380000 | D31: 400000 | E31: 460000 | F31: 520000 | G31: 600000 | H31: 660000 | I31: $ | J31: Model methodology | K31: Estimate/Projection
A32: STM base (full-season equivalents) | B32: TICKETING | C32: 2300 | D32: 2350 | E32: 2450 | F32: 2550 | G32: 2700 | H32: 2780 | I32: FSE | J32: Model methodology | K32: Estimate/Projection
A33: STM retention rate | B33: TICKETING | C33: 0.77 | D33: 0.76 | E33: 0.78 | F33: 0.8 | G33: 0.82 | H33: 0.83 | I33: pct | J33: Model methodology | K33: Estimate/Projection
A34: F&B per-cap gross | B34: ANCILLARY | C34: 13 | D34: 13.4 | E34: 14 | F34: 14.8 | G34: 15.5 | I34: $/attendee | J34: Model methodology | K34: Estimate/Projection
A35: Team concession commission rate | B35: ANCILLARY | C35: 0.04 | D35: 0.04 | E35: 0.04 | F35: 0.04 | G35: 0.04 | H35: 0.04 | I35: pct | J35: Model methodology | K35: Estimate
A36: Merchandise per-cap | B36: ANCILLARY | C36: 3.6 | D36: 3.8 | E36: 4 | F36: 4.2 | G36: 4.5 | I36: $/attendee | J36: Model methodology | K36: Estimate/Projection
A37: Parking fee assumption | B37: ANCILLARY | C37: 15 | D37: 15 | E37: 15 | F37: 18 | G37: 20 | H37: 21 | I37: $/vehicle | J37: https://pechangaarenasd.com/plan-your-visit/directions-parking/ | K37: Estimate/Projection
A38: Average auto occupancy | B38: ANCILLARY | C38: 2.6 | D38: 2.6 | E38: 2.6 | F38: 2.5 | G38: 2.5 | H38: 2.5 | I38: persons/vehicle | J38: Model methodology | K38: Estimate
A39: Team share of parking | B39: ANCILLARY | C39: 0.05 | D39: 0.05 | E39: 0.05 | F39: 0.05 | G39: 0.05 | H39: 0.05 | I39: pct | J39: Model methodology | K39: Estimate
A40: Total sponsorship revenue | B40: SPONSORSHIP | C40: 1950000 | D40: 2000000 | E40: 2200000 | F40: 2450000 | G40: 2700000 | I40: $ | J40: Model methodology | K40: Estimate/Projection
A41: Title partner value | B41: SPONSORSHIP | C41: 450000 | D41: 450000 | E41: 480000 | F41: 500000 | G41: 550000 | H41: 580000 | I41: $ | J41: Model methodology | K41: Estimate
A42: Jersey / patch revenue | B42: SPONSORSHIP | C42: 0 | D42: 0 | E42: 150000 | F42: 180000 | G42: 200000 | H42: 220000 | I42: $ | J42: Model methodology | K42: Estimate
A43: Digital inventory yield | B43: SPONSORSHIP | C43: 80000 | D43: 90000 | E43: 110000 | F43: 130000 | G43: 150000 | H43: 165000 | I43: $ | J43: Model methodology | K43: Estimate
A44: Broadcast / streaming value | B44: MEDIA | C44: 150000 | D44: 100000 | E44: 100000 | F44: 110000 | G44: 130000 | H44: 145000 | I44: $ | J44: https://theahl.com/news/ahl-flosports-partnership-extension | K44: Estimate
A45: Email subscribers (estimated active) | B45: DIGITAL | C45: 18000 | D45: 19000 | E45: 20000 | F45: 21000 | G45: 22000 | H45: 23000 | I45: subs | J45: Model methodology | K45: Estimate
A46: Social audience (aggregate est.) | B46: DIGITAL | C46: 150000 | D46: 165000 | E46: 180000 | F46: 195000 | G46: 205000 | H46: 215000 | I46: followers | J46: Multiple public social snippets | K46: Estimate
A47: Website monthly visits | B47: DIGITAL | C47: 28000 | D47: 29000 | E47: 31000 | F47: 33000 | G47: 35200 | I47: visits | J47: https://www.similarweb.com/website/sandiegogulls.com/ | K47: Estimate/Projection
A48: Bounce rate | B48: DIGITAL | C48: 0.5 | D48: 0.495 | E48: 0.49 | F48: 0.48 | G48: 0.4725 | H48: 0.465 | I48: pct | J48: https://www.similarweb.com/website/sandiegogulls.com/ | K48: Estimate/Projection
A49: Pages per visit | B49: DIGITAL | C49: 1.55 | D49: 1.6 | E49: 1.65 | F49: 1.72 | G49: 1.8 | H49: 1.9 | I49: pages | J49: https://www.similarweb.com/website/sandiegogulls.com/ | K49: Estimate/Projection
A50: Average visit duration (sec) | B50: DIGITAL | C50: 60 | D50: 62 | E50: 65 | F50: 68 | G50: 70 | H50: 75 | I50: sec | J50: https://www.similarweb.com/website/sandiegogulls.com/ | K50: Estimate/Projection
A51: Organic search share | B51: DIGITAL | C51: 0.4 | D51: 0.41 | E51: 0.43 | F51: 0.44 | G51: 0.4551 | H51: 0.46 | I51: pct | J51: https://www.similarweb.com/website/sandiegogulls.com/ | K51: Estimate/Projection
A52: Customer acquisition cost | B52: MARKETING | C52: 45 | D52: 44 | E52: 42 | F52: 40 | G52: 39 | H52: 37 | I52: $/new buyer | J52: Model methodology | K52: Estimate
A53: Net promoter score | B53: MARKETING | C53: 45 | D53: 43 | E53: 46 | F53: 50 | G53: 54 | H53: 56 | I53: pts | J53: Model methodology | K53: Estimate
A54: Facility fee per paid ticket | B54: ARENA | E54: 2.5 | F54: 3 | G54: 3 | H54: 3 | I54: $/ticket | J54: Lease-era reporting / model assumption | K54: Estimate
A55: Base rent floor (annualized) | B55: ARENA | E55: 775716 | F55: 799107 | G55: 823084 | H55: 839546 | I55: $ | J55: https://www.lee-associates.com/elee/utc/newsletter/091224/article3.pdf | K55: Public/Projection
A56: Rent escalator | B56: ARENA | F56: 0.03 | G56: 0.03 | H56: 0.02 | I56: pct | J56: Lease-era reporting / model assumption | K56: Derived/Projection
A57: Security / police overhead per event | B57: ARENA | C57: 12000 | D57: 12000 | E57: 13000 | F57: 14000 | G57: 15000 | H57: 15500 | I57: $ | J57: https://www.sandiego.gov/sites/default/files/specialeventsopsmanual2020.pdf | K57: Estimate
A58: Utilities & HVAC load | B58: ARENA | C58: 180000 | D58: 190000 | E58: 210000 | F58: 230000 | G58: 250000 | H58: 260000 | I58: $ | J58: Model methodology | K58: Estimate
A59: Load-in / load-out allocation | B59: ARENA | C59: 80000 | D59: 85000 | E59: 90000 | F59: 95000 | G59: 100000 | H59: 105000 | I59: $ | J59: Model methodology | K59: Estimate
A60: Midway district assessment / CFD | B60: ARENA | C60: 0 | D60: 0 | E60: 0 | F60: 0 | G60: 0 | H60: 0 | I60: $ | J60: Public review | K60: Context
A61: Lease horizon (months remaining) | B61: ARENA | E61: 29 | F61: 17 | G61: 5 | H61: 0 | I61: months | J61: https://www.sandiego.gov/economic-development/real-estate/midway-rising | K61: Estimate
A62: Naming-rights tranche allocable to team ops | B62: ARENA | C62: 250000 | D62: 250000 | E62: 260000 | F62: 275000 | G62: 300000 | H62: 310000 | I62: $ | J62: Model methodology | K62: Estimate
A63: Tax liability | B63: ARENA | C63: 50000 | D63: 50000 | E63: 50000 | F63: 50000 | G63: 50000 | H63: 50000 | I63: $ | J63: Model methodology | K63: Estimate
A64: Debt-to-value ratio | B64: ARENA | C64: 0.05 | D64: 0.05 | E64: 0.05 | F64: 0.05 | G64: 0.05 | H64: 0.05 | I64: pct | J64: Model methodology | K64: Estimate
A65: Roster headcount | B65: HUMAN CAPITAL | C65: 22 | D65: 24 | E65: 26 | F65: 22 | G65: 29 | H65: 29 | I65: players | J65: Multiple official roster/game notes sources | K65: Public/Projection
A66: Coaching staff payroll | B66: HUMAN CAPITAL | C66: 550000 | D66: 560000 | E66: 580000 | F66: 620000 | G66: 680000 | H66: 710000 | I66: $ | J66: Model methodology | K66: Estimate
A67: Front office FTE | B67: HUMAN CAPITAL | C67: 42 | D67: 43 | E67: 44 | F67: 45 | G67: 46 | H67: 47 | I67: FTE | J67: https://www.linkedin.com/company/san-diego-gulls | K67: Estimate
A68: Medical / training tech spend | B68: HUMAN CAPITAL | C68: 100000 | D68: 110000 | E68: 130000 | F68: 150000 | G68: 175000 | H68: 185000 | I68: $ | J68: Model methodology | K68: Estimate
A69: Travel logistics ratio (air-heavy) | B69: HUMAN CAPITAL | C69: 0.82 | D69: 0.82 | E69: 0.83 | F69: 0.84 | G69: 0.84 | H69: 0.84 | I69: pct | J69: Model methodology | K69: Estimate
A70: Player housing spend | B70: HUMAN CAPITAL | C70: 200000 | D70: 210000 | E70: 230000 | F70: 250000 | G70: 280000 | H70: 290000 | I70: $ | J70: Model methodology | K70: Estimate
A71: AHL-only salary floor | B71: HUMAN CAPITAL | C71: 49000 | D71: 50000 | E71: 51500 | F71: 52725 | G71: 54000 | H71: 55620 | I71: $ | J71: https://phpa.com/site/agreements | K71: Estimate/Projection
A72: AHL-only average salary | B72: HUMAN CAPITAL | C72: 65000 | D72: 66000 | E72: 70000 | F72: 74000 | G72: 78000 | H72: 80000 | I72: $ | J72: Model methodology | K72: Estimate
A73: Insurance premiums | B73: HUMAN CAPITAL | C73: 200000 | D73: 210000 | E73: 230000 | F73: 250000 | G73: 270000 | H73: 280000 | I73: $ | J73: Model methodology | K73: Estimate
... A82: Email database value per active subscriber | B82: DIGITAL | C82: 5 | D82: 5 | E82: 5 | F82: 5 | G82: 5 | H82: 5 | I82: $/active sub | J82: Model control | K82: Control

Sheet Charts
A1: Dynamic Charts
A3: Metric | B3: 2021-22 | C3: 2022-23 | D3: 2023-24 | E3: 2024-25 | F3: 2025-26 | G3: 2026-27
A4: Average Attendance | B4: =IFERROR(Master_Model!E6,0) | C4: =IFERROR(Master_Model!F6,0) | D4: =IFERROR(Master_Model!G6,0) | E4: =IFERROR(Master_Model!H6,0) | F4: =IFERROR(Master_Model!I6,0) | G4: =IFERROR(Master_Model!J6,0)
A5: Gross Revenue | B5: =IFERROR(Master_Model!E52,0) | C5: =IFERROR(Master_Model!F52,0) | D5: =IFERROR(Master_Model!G52,0) | E5: =IFERROR(Master_Model!H52,0) | F5: =IFERROR(Master_Model!I52,0) | G5: =IFERROR(Master_Model!J52,0)
A6: EBITDA | B6: =IFERROR(Master_Model!E98,0) | C6: =IFERROR(Master_Model!F98,0) | D6: =IFERROR(Master_Model!G98,0) | E6: =IFERROR(Master_Model!H98,0) | F6: =IFERROR(Master_Model!I98,0) | G6: =IFERROR(Master_Model!J98,0)
A7: Implied Valuation | B7: =IFERROR(Master_Model!E102,0) | C7: =IFERROR(Master_Model!F102,0) | D7: =IFERROR(Master_Model!G102,0) | E7: =IFERROR(Master_Model!H102,0) | F7: =IFERROR(Master_Model!I102,0) | G7: =IFERROR(Master_Model!J102,0)

Sheet Export_PDF_Macro
A1: PDF Export Macro (ready-to-paste VBA)
A2: A live VBA module cannot be embedded from this environment, but the code below is ready to paste into Excel VBA and assign to a button.
A4: Sub ExportAssessmentPDF() Sheets(Array("Scenario_OnePager", "Charts")).Select ActiveSheet.ExportAsFixedFormat Type:=xlTypePDF, _ Filename:=ThisWorkbook.Path & "\\San_Diego_Gulls_Assessment.pdf", _ Quality:=xlQualityStandard, IncludeDocProperties:=True, _ IgnorePrintAreas:=False, OpenAfterPublish:=False Sheets("Executive_Dashboard").Select End Sub
